[{
  "_id": {
    "$oid": "68a8184ce9320c1361e8af19"
  },
  "id": 1,
  "name": "Durian Montong",
  "qrCode": "KTD-DM-001",
  "owner": "Ahmad Wijaya",
  "fotoGambar": "https://picsum.photos/seed/durian-montong/640/640",
  "memberId": "KOP-001",
  "contractNumber": "CTR-2023-08-001",
  "location": "Blok A, Zona 1",
  "plantType": "Buah",
  "status": "Panen",
  "lastUpdate": "22/8/2025",
  "history": [
    {
      "id": 1755848188798,
      "type": "Panen",
      "date": "22/8/2025",
      "description": "Dousna",
      "hasImage": true,
      "imageUrl": "https://ik.imagekit.io/niyfabfxr/plant-photos/plant-1755848185837-Event_Page_HIr9vwCB2.png",
      "_id": {
        "$oid": "68a81e113d3293fa7479ac16"
      }
    },
    {
      "id": 2,
      "type": "Persiapan Bibit",
      "date": "15/7/2025",
      "description": "Bibit durian unggul siap tanam.",
      "hasImage": true,
      "imageUrl": null,
      "_id": {
        "$oid": "68a8184ce9320c1361e8af1b"
      }
    },
    {
      "id": 3,
      "type": "Buka Lahan",
      "date": "10/7/2025",
      "description": "Pembersihan lahan tanam seluas 0.5 hektar.",
      "hasImage": true,
      "imageUrl": null,
      "_id": {
        "$oid": "68a8184ce9320c1361e8af1c"
      }
    }
  ],
  "__v": 0,
  "createdAt": {
    "$date": "2025-08-22T07:12:12.893Z"
  },
  "updatedAt": {
    "$date": "2025-08-22T07:36:49.912Z"
  }
},
{
  "_id": {
    "$oid": "68a8184ce9320c1361e8af1d"
  },
  "id": 2,
  "name": "Gaharu",
  "qrCode": "KTD-GH-002",
  "owner": "Budi Santoso",
  "fotoGambar": "https://picsum.photos/seed/gaharu/640/640",
  "memberId": "KOP-002",
  "contractNumber": "CTR-2023-08-002",
  "location": "Blok A, Zona 2",
  "plantType": "Kayu",
  "status": "Persiapan Bibit",
  "lastUpdate": "18/7/2025",
  "history": [
    {
      "id": 1,
      "type": "Persiapan Bibit",
      "date": "18/7/2025",
      "description": "Bibit gaharu unggul siap tanam.",
      "hasImage": true,
      "imageUrl": null,
      "_id": {
        "$oid": "68a8184ce9320c1361e8af1e"
      }
    },
    {
      "id": 2,
      "type": "Buka Lahan",
      "date": "12/7/2025",
      "description": "Pembersihan lahan tanam seluas 1 hektar.",
      "hasImage": true,
      "imageUrl": null,
      "_id": {
        "$oid": "68a8184ce9320c1361e8af1f"
      }
    }
  ],
  "__v": 0,
  "createdAt": {
    "$date": "2025-08-22T07:12:12.894Z"
  },
  "updatedAt": {
    "$date": "2025-08-22T07:13:59.847Z"
  }
},
{
  "_id": {
    "$oid": "68a8184ce9320c1361e8af20"
  },
  "id": 3,
  "name": "Mangga Harum Manis",
  "qrCode": "KTD-MH-003",
  "owner": "Siti Rahayu",
  "fotoGambar": "https://picsum.photos/seed/mangga-harum-manis/640/640",
  "memberId": "KOP-003",
  "contractNumber": "CTR-2023-08-003",
  "location": "Blok B, Zona 1",
  "plantType": "Buah",
  "status": "Kontrak Baru",
  "lastUpdate": "16/7/2025",
  "history": [
    {
      "id": 1,
      "type": "Kontrak Baru",
      "date": "16/7/2025",
      "description": "Kontrak penanaman mangga harum manis.",
      "hasImage": true,
      "imageUrl": null,
      "_id": {
        "$oid": "68a8184ce9320c1361e8af21"
      }
    }
  ],
  "__v": 0,
  "createdAt": {
    "$date": "2025-08-22T07:12:12.894Z"
  },
  "updatedAt": {
    "$date": "2025-08-22T07:13:59.874Z"
  }
},
{
  "_id": {
    "$oid": "68a8184ce9320c1361e8af22"
  },
  "id": 4,
  "name": "Alpukat Mentega",
  "qrCode": "KTD-AM-004",
  "owner": "Dewi Lestari",
  "fotoGambar": "https://picsum.photos/seed/alpukat-mentega/640/640",
  "memberId": "KOP-004",
  "contractNumber": "CTR-2023-08-004",
  "location": "Blok B, Zona 2",
  "plantType": "Buah",
  "status": "Pemupukan",
  "lastUpdate": "14/7/2025",
  "history": [
    {
      "id": 1,
      "type": "Pemupukan",
      "date": "14/7/2025",
      "description": "Pemupukan NPK dosis 10gr per tanaman alpukat.",
      "hasImage": true,
      "imageUrl": null,
      "_id": {
        "$oid": "68a8184ce9320c1361e8af23"
      }
    },
    {
      "id": 2,
      "type": "Tanam Bibit",
      "date": "10/7/2025",
      "description": "Penanaman bibit alpukat mentega.",
      "hasImage": true,
      "imageUrl": null,
      "_id": {
        "$oid": "68a8184ce9320c1361e8af24"
      }
    }
  ],
  "__v": 0,
  "createdAt": {
    "$date": "2025-08-22T07:12:12.895Z"
  },
  "updatedAt": {
    "$date": "2025-08-22T07:13:59.897Z"
  }
},
{
  "_id": {
    "$oid": "68a8184ce9320c1361e8af25"
  },
  "id": 5,
  "name": "Jengkol",
  "qrCode": "KTD-JK-005",
  "owner": "Andi Rahman",
  "fotoGambar": "https://picsum.photos/seed/jengkol/640/640",
  "memberId": "KOP-005",
  "contractNumber": "CTR-2023-08-005",
  "location": "Blok C, Zona 1",
  "plantType": "Sayuran",
  "status": "Panen",
  "lastUpdate": "12/7/2025",
  "history": [
    {
      "id": 1,
      "type": "Panen",
      "date": "12/7/2025",
      "description": "Panen jengkol hasil 50kg per pohon.",
      "hasImage": true,
      "imageUrl": null,
      "_id": {
        "$oid": "68a8184ce9320c1361e8af26"
      }
    },
    {
      "id": 2,
      "type": "Pemeliharaan",
      "date": "5/7/2025",
      "description": "Pemangkasan dan perawatan rutin.",
      "hasImage": true,
      "imageUrl": null,
      "_id": {
        "$oid": "68a8184ce9320c1361e8af27"
      }
    }
  ],
  "__v": 0,
  "createdAt": {
    "$date": "2025-08-22T07:12:12.895Z"
  },
  "updatedAt": {
    "$date": "2025-08-22T07:13:59.921Z"
  }
},
{
  "_id": {
    "$oid": "68a8184ce9320c1361e8af28"
  },
  "id": 6,
  "name": "Aren",
  "qrCode": "KTD-AR-006",
  "owner": "Bambang Sutrisno",
  "fotoGambar": "https://picsum.photos/seed/aren/640/640",
  "memberId": "KOP-006",
  "contractNumber": "CTR-2023-08-006",
  "location": "Blok C, Zona 2",
  "plantType": "Kayu",
  "status": "Tanam Bibit",
  "lastUpdate": "8/7/2025",
  "history": [
    {
      "id": 1,
      "type": "Tanam Bibit",
      "date": "8/7/2025",
      "description": "Penanaman bibit aren di lokasi Blok C, Zona 2.",
      "hasImage": true,
      "imageUrl": null,
      "_id": {
        "$oid": "68a8184ce9320c1361e8af29"
      }
    }
  ],
  "__v": 0,
  "createdAt": {
    "$date": "2025-08-22T07:12:12.895Z"
  },
  "updatedAt": {
    "$date": "2025-08-22T07:13:59.943Z"
  }
},
{
  "_id": {
    "$oid": "68a8184ce9320c1361e8af2a"
  },
  "id": 7,
  "name": "Rambutan Binjai",
  "qrCode": "KTD-RB-007",
  "owner": "Indira Sari",
  "fotoGambar": "https://picsum.photos/seed/rambutan-binjai/640/640",
  "memberId": "KOP-007",
  "contractNumber": "CTR-2023-08-007",
  "location": "Blok D, Zona 1",
  "plantType": "Buah",
  "status": "Persiapan Bibit",
  "lastUpdate": "6/7/2025",
  "history": [
    {
      "id": 1,
      "type": "Persiapan Bibit",
      "date": "6/7/2025",
      "description": "Bibit rambutan binjai siap tanam.",
      "hasImage": true,
      "imageUrl": null,
      "_id": {
        "$oid": "68a8184ce9320c1361e8af2b"
      }
    }
  ],
  "__v": 0,
  "createdAt": {
    "$date": "2025-08-22T07:12:12.895Z"
  },
  "updatedAt": {
    "$date": "2025-08-22T07:13:59.966Z"
  }
},
{
  "_id": {
    "$oid": "68a8184ce9320c1361e8af2c"
  },
  "id": 8,
  "name": "Jahe Merah",
  "qrCode": "KTD-JM-008",
  "owner": "Hendra Kusuma",
  "fotoGambar": "https://picsum.photos/seed/jahe-merah/640/640",
  "memberId": "KOP-008",
  "contractNumber": "CTR-2023-08-008",
  "location": "Blok D, Zona 2",
  "plantType": "Rempah",
  "status": "Kontrak Baru",
  "lastUpdate": "4/7/2025",
  "history": [
    {
      "id": 1,
      "type": "Kontrak Baru",
      "date": "4/7/2025",
      "description": "Kontrak penanaman jahe merah.",
      "hasImage": true,
      "imageUrl": null,
      "_id": {
        "$oid": "68a8184ce9320c1361e8af2d"
      }
    }
  ],
  "__v": 0,
  "createdAt": {
    "$date": "2025-08-22T07:12:12.895Z"
  },
  "updatedAt": {
    "$date": "2025-08-22T07:14:00.019Z"
  }
},
{
  "_id": {
    "$oid": "68a8184ce9320c1361e8af2e"
  },
  "id": 9,
  "name": "Kelapa Sawit",
  "qrCode": "KTD-KS-009",
  "owner": "Ratna Dewi",
  "fotoGambar": "https://picsum.photos/seed/kelapa-sawit/640/640",
  "memberId": "KOP-009",
  "contractNumber": "CTR-2023-08-009",
  "location": "Blok E, Zona 1",
  "plantType": "Industri",
  "status": "Pemupukan",
  "lastUpdate": "2/7/2025",
  "history": [
    {
      "id": 1,
      "type": "Pemupukan",
      "date": "2/7/2025",
      "description": "Pemupukan NPK untuk kelapa sawit.",
      "hasImage": true,
      "imageUrl": null,
      "_id": {
        "$oid": "68a8184ce9320c1361e8af2f"
      }
    }
  ],
  "__v": 0,
  "createdAt": {
    "$date": "2025-08-22T07:12:12.895Z"
  },
  "updatedAt": {
    "$date": "2025-08-22T07:14:00.042Z"
  }
},
{
  "_id": {
    "$oid": "68a8184ce9320c1361e8af30"
  },
  "id": 10,
  "name": "Karet",
  "qrCode": "KTD-KR-010",
  "owner": "Joko Widodo",
  "fotoGambar": "https://picsum.photos/seed/karet/640/640",
  "memberId": "KOP-010",
  "contractNumber": "CTR-2023-08-010",
  "location": "Blok E, Zona 2",
  "plantType": "Industri",
  "status": "Tanam Bibit",
  "lastUpdate": "30/6/2025",
  "history": [
    {
      "id": 1,
      "type": "Tanam Bibit",
      "date": "30/6/2025",
      "description": "Penanaman bibit karet unggul.",
      "hasImage": true,
      "imageUrl": null,
      "_id": {
        "$oid": "68a8184ce9320c1361e8af31"
      }
    }
  ],
  "__v": 0,
  "createdAt": {
    "$date": "2025-08-22T07:12:12.895Z"
  },
  "updatedAt": {
    "$date": "2025-08-22T07:14:00.065Z"
  }
},
{
  "_id": {
    "$oid": "68a8184ce9320c1361e8af32"
  },
  "id": 11,
  "name": "Cengkeh",
  "qrCode": "KTD-CK-011",
  "owner": "Sri Mulyani",
  "fotoGambar": "https://picsum.photos/seed/cengkeh/640/640",
  "memberId": "KOP-011",
  "contractNumber": "CTR-2023-08-011",
  "location": "Blok F, Zona 1",
  "plantType": "Rempah",
  "status": "Persiapan Bibit",
  "lastUpdate": "28/6/2025",
  "history": [
    {
      "id": 1,
      "type": "Persiapan Bibit",
      "date": "28/6/2025",
      "description": "Bibit cengkeh siap untuk penanaman.",
      "hasImage": true,
      "imageUrl": null,
      "_id": {
        "$oid": "68a8184ce9320c1361e8af33"
      }
    }
  ],
  "__v": 0,
  "createdAt": {
    "$date": "2025-08-22T07:12:12.895Z"
  },
  "updatedAt": {
    "$date": "2025-08-22T07:14:00.089Z"
  }
},
{
  "_id": {
    "$oid": "68a8184ce9320c1361e8af34"
  },
  "id": 12,
  "name": "Pala",
  "qrCode": "KTD-PL-012",
  "owner": "Agus Salim",
  "fotoGambar": "https://picsum.photos/seed/pala/640/640",
  "memberId": "KOP-012",
  "contractNumber": "CTR-2023-08-012",
  "location": "Blok F, Zona 2",
  "plantType": "Rempah",
  "status": "Kontrak Baru",
  "lastUpdate": "26/6/2025",
  "history": [
    {
      "id": 1,
      "type": "Kontrak Baru",
      "date": "26/6/2025",
      "description": "Kontrak penanaman pala.",
      "hasImage": true,
      "imageUrl": null,
      "_id": {
        "$oid": "68a8184ce9320c1361e8af35"
      }
    }
  ],
  "__v": 0,
  "createdAt": {
    "$date": "2025-08-22T07:12:12.895Z"
  },
  "updatedAt": {
    "$date": "2025-08-22T07:14:00.112Z"
  }
},
{
  "_id": {
    "$oid": "68a8184ce9320c1361e8af36"
  },
  "id": 13,
  "name": "Kakao",
  "qrCode": "KTD-KK-013",
  "owner": "Maya Sari",
  "fotoGambar": "https://picsum.photos/seed/kakao/640/640",
  "memberId": "KOP-013",
  "contractNumber": "CTR-2023-08-013",
  "location": "Blok G, Zona 1",
  "plantType": "Industri",
  "status": "Pemupukan",
  "lastUpdate": "24/6/2025",
  "history": [
    {
      "id": 1,
      "type": "Pemupukan",
      "date": "24/6/2025",
      "description": "Pemupukan organik untuk tanaman kakao.",
      "hasImage": true,
      "imageUrl": null,
      "_id": {
        "$oid": "68a8184ce9320c1361e8af37"
      }
    }
  ],
  "__v": 0,
  "createdAt": {
    "$date": "2025-08-22T07:12:12.895Z"
  },
  "updatedAt": {
    "$date": "2025-08-22T07:14:00.152Z"
  }
},
{
  "_id": {
    "$oid": "68a8184ce9320c1361e8af38"
  },
  "id": 14,
  "name": "Kopi Arabika",
  "qrCode": "KTD-KA-014",
  "owner": "Dedi Kurniawan",
  "fotoGambar": "https://picsum.photos/seed/kopi-arabika/640/640",
  "memberId": "KOP-014",
  "contractNumber": "CTR-2023-08-014",
  "location": "Blok G, Zona 2",
  "plantType": "Industri",
  "status": "Tanam Bibit",
  "lastUpdate": "22/6/2025",
  "history": [
    {
      "id": 1,
      "type": "Tanam Bibit",
      "date": "22/6/2025",
      "description": "Penanaman bibit kopi arabika premium.",
      "hasImage": true,
      "imageUrl": null,
      "_id": {
        "$oid": "68a8184ce9320c1361e8af39"
      }
    }
  ],
  "__v": 0,
  "createdAt": {
    "$date": "2025-08-22T07:12:12.896Z"
  },
  "updatedAt": {
    "$date": "2025-08-22T07:14:00.175Z"
  }
},
{
  "_id": {
    "$oid": "68a8184ce9320c1361e8af3a"
  },
  "id": 15,
  "name": "Vanili",
  "qrCode": "KTD-VN-015",
  "owner": "Lina Marlina",
  "fotoGambar": "https://picsum.photos/seed/vanili/640/640",
  "memberId": "KOP-015",
  "contractNumber": "CTR-2023-08-015",
  "location": "Blok H, Zona 1",
  "plantType": "Rempah",
  "status": "Persiapan Bibit",
  "lastUpdate": "20/6/2025",
  "history": [
    {
      "id": 1,
      "type": "Persiapan Bibit",
      "date": "20/6/2025",
      "description": "Bibit vanili siap untuk penanaman.",
      "hasImage": true,
      "imageUrl": null,
      "_id": {
        "$oid": "68a8184ce9320c1361e8af3b"
      }
    }
  ],
  "__v": 0,
  "createdAt": {
    "$date": "2025-08-22T07:12:12.896Z"
  },
  "updatedAt": {
    "$date": "2025-08-22T07:14:00.198Z"
  }
},
{
  "_id": {
    "$oid": "68a8184ce9320c1361e8af3c"
  },
  "id": 16,
  "name": "Lada Hitam",
  "qrCode": "KTD-LH-016",
  "owner": "Rudi Hartono",
  "fotoGambar": "https://picsum.photos/seed/lada-hitam/640/640",
  "memberId": "KOP-016",
  "contractNumber": "CTR-2023-08-016",
  "location": "Blok H, Zona 2",
  "plantType": "Rempah",
  "status": "Kontrak Baru",
  "lastUpdate": "18/6/2025",
  "history": [
    {
      "id": 1,
      "type": "Kontrak Baru",
      "date": "18/6/2025",
      "description": "Kontrak penanaman lada hitam.",
      "hasImage": true,
      "imageUrl": null,
      "_id": {
        "$oid": "68a8184ce9320c1361e8af3d"
      }
    }
  ],
  "__v": 0,
  "createdAt": {
    "$date": "2025-08-22T07:12:12.896Z"
  },
  "updatedAt": {
    "$date": "2025-08-22T07:14:00.221Z"
  }
},
{
  "_id": {
    "$oid": "68a8184ce9320c1361e8af3e"
  },
  "id": 17,
  "name": "Kemiri",
  "qrCode": "KTD-KM-017",
  "owner": "Sari Indah",
  "fotoGambar": "https://picsum.photos/seed/kemiri/640/640",
  "memberId": "KOP-017",
  "contractNumber": "CTR-2023-08-017",
  "location": "Blok I, Zona 1",
  "plantType": "Rempah",
  "status": "Pemupukan",
  "lastUpdate": "16/6/2025",
  "history": [
    {
      "id": 1,
      "type": "Pemupukan",
      "date": "16/6/2025",
      "description": "Pemupukan untuk tanaman kemiri.",
      "hasImage": true,
      "imageUrl": null,
      "_id": {
        "$oid": "68a8184ce9320c1361e8af3f"
      }
    }
  ],
  "__v": 0,
  "createdAt": {
    "$date": "2025-08-22T07:12:12.896Z"
  },
  "updatedAt": {
    "$date": "2025-08-22T07:14:00.244Z"
  }
},
{
  "_id": {
    "$oid": "68a8184ce9320c1361e8af40"
  },
  "id": 18,
  "name": "Jati",
  "qrCode": "KTD-JT-018",
  "owner": "Budi Prasetyo",
  "fotoGambar": "https://picsum.photos/seed/jati/640/640",
  "memberId": "KOP-018",
  "contractNumber": "CTR-2023-08-018",
  "location": "Blok I, Zona 2",
  "plantType": "Kayu",
  "status": "Tanam Bibit",
  "lastUpdate": "14/6/2025",
  "history": [
    {
      "id": 1,
      "type": "Tanam Bibit",
      "date": "14/6/2025",
      "description": "Penanaman bibit jati unggul.",
      "hasImage": true,
      "imageUrl": null,
      "_id": {
        "$oid": "68a8184ce9320c1361e8af41"
      }
    }
  ],
  "__v": 0,
  "createdAt": {
    "$date": "2025-08-22T07:12:12.896Z"
  },
  "updatedAt": {
    "$date": "2025-08-22T07:14:00.267Z"
  }
},
{
  "_id": {
    "$oid": "68a8184ce9320c1361e8af42"
  },
  "id": 19,
  "name": "Mahoni",
  "qrCode": "KTD-MH-019",
  "owner": "Ani Suryani",
  "fotoGambar": "https://picsum.photos/seed/mahoni/640/640",
  "memberId": "KOP-019",
  "contractNumber": "CTR-2023-08-019",
  "location": "Blok J, Zona 1",
  "plantType": "Kayu",
  "status": "Persiapan Bibit",
  "lastUpdate": "12/6/2025",
  "history": [
    {
      "id": 1,
      "type": "Persiapan Bibit",
      "date": "12/6/2025",
      "description": "Bibit mahoni siap untuk penanaman.",
      "hasImage": true,
      "imageUrl": null,
      "_id": {
        "$oid": "68a8184ce9320c1361e8af43"
      }
    }
  ],
  "__v": 0,
  "createdAt": {
    "$date": "2025-08-22T07:12:12.896Z"
  },
  "updatedAt": {
    "$date": "2025-08-22T07:14:00.289Z"
  }
},
{
  "_id": {
    "$oid": "68a8184ce9320c1361e8af44"
  },
  "id": 20,
  "name": "Sengon",
  "qrCode": "KTD-SG-020",
  "owner": "Eko Susanto",
  "fotoGambar": "https://picsum.photos/seed/sengon/640/640",
  "memberId": "KOP-020",
  "contractNumber": "CTR-2023-08-020",
  "location": "Blok J, Zona 2",
  "plantType": "Kayu",
  "status": "Kontrak Baru",
  "lastUpdate": "10/6/2025",
  "history": [
    {
      "id": 1,
      "type": "Kontrak Baru",
      "date": "10/6/2025",
      "description": "Kontrak penanaman sengon.",
      "hasImage": true,
      "imageUrl": null,
      "_id": {
        "$oid": "68a8184ce9320c1361e8af45"
      }
    }
  ],
  "__v": 0,
  "createdAt": {
    "$date": "2025-08-22T07:12:12.896Z"
  },
  "updatedAt": {
    "$date": "2025-08-22T07:14:00.312Z"
  }
},
{
  "_id": {
    "$oid": "68a8184ce9320c1361e8af46"
  },
  "id": 21,
  "name": "Temulawak",
  "qrCode": "KTD-TL-021",
  "owner": "Fitri Handayani",
  "fotoGambar": "https://picsum.photos/seed/temulawak/640/640",
  "memberId": "KOP-021",
  "contractNumber": "CTR-2023-08-021",
  "location": "Blok K, Zona 1",
  "plantType": "Obat",
  "status": "Pemupukan",
  "lastUpdate": "8/6/2025",
  "history": [
    {
      "id": 1,
      "type": "Pemupukan",
      "date": "8/6/2025",
      "description": "Pemupukan organik untuk temulawak.",
      "hasImage": true,
      "imageUrl": null,
      "_id": {
        "$oid": "68a8184ce9320c1361e8af47"
      }
    }
  ],
  "__v": 0,
  "createdAt": {
    "$date": "2025-08-22T07:12:12.896Z"
  },
  "updatedAt": {
    "$date": "2025-08-22T07:14:00.336Z"
  }
},
{
  "_id": {
    "$oid": "68a8184ce9320c1361e8af48"
  },
  "id": 22,
  "name": "Kunyit",
  "qrCode": "KTD-KN-022",
  "owner": "Hadi Wijaya",
  "fotoGambar": "https://picsum.photos/seed/kunyit/640/640",
  "memberId": "KOP-022",
  "contractNumber": "CTR-2023-08-022",
  "location": "Blok K, Zona 2",
  "plantType": "Obat",
  "status": "Tanam Bibit",
  "lastUpdate": "6/6/2025",
  "history": [
    {
      "id": 1,
      "type": "Tanam Bibit",
      "date": "6/6/2025",
      "description": "Penanaman bibit kunyit.",
      "hasImage": true,
      "imageUrl": null,
      "_id": {
        "$oid": "68a8184ce9320c1361e8af49"
      }
    }
  ],
  "__v": 0,
  "createdAt": {
    "$date": "2025-08-22T07:12:12.896Z"
  },
  "updatedAt": {
    "$date": "2025-08-22T07:14:00.358Z"
  }
},
{
  "_id": {
    "$oid": "68a8184ce9320c1361e8af4a"
  },
  "id": 23,
  "name": "Lengkuas",
  "qrCode": "KTD-LK-023",
  "owner": "Rina Sari",
  "fotoGambar": "https://picsum.photos/seed/lengkuas/640/640",
  "memberId": "KOP-023",
  "contractNumber": "CTR-2023-08-023",
  "location": "Blok L, Zona 1",
  "plantType": "Rempah",
  "status": "Persiapan Bibit",
  "lastUpdate": "4/6/2025",
  "history": [
    {
      "id": 1,
      "type": "Persiapan Bibit",
      "date": "4/6/2025",
      "description": "Bibit lengkuas siap untuk penanaman.",
      "hasImage": true,
      "imageUrl": null,
      "_id": {
        "$oid": "68a8184ce9320c1361e8af4b"
      }
    }
  ],
  "__v": 0,
  "createdAt": {
    "$date": "2025-08-22T07:12:12.896Z"
  },
  "updatedAt": {
    "$date": "2025-08-22T07:14:00.381Z"
  }
},
{
  "_id": {
    "$oid": "68a8184ce9320c1361e8af4c"
  },
  "id": 24,
  "name": "Kencur",
  "qrCode": "KTD-KC-024",
  "owner": "Tono Sugiarto",
  "fotoGambar": "https://picsum.photos/seed/kencur/640/640",
  "memberId": "KOP-024",
  "contractNumber": "CTR-2023-08-024",
  "location": "Blok L, Zona 2",
  "plantType": "Obat",
  "status": "Kontrak Baru",
  "lastUpdate": "2/6/2025",
  "history": [
    {
      "id": 1,
      "type": "Kontrak Baru",
      "date": "2/6/2025",
      "description": "Kontrak penanaman kencur.",
      "hasImage": true,
      "imageUrl": null,
      "_id": {
        "$oid": "68a8184ce9320c1361e8af4d"
      }
    }
  ],
  "__v": 0,
  "createdAt": {
    "$date": "2025-08-22T07:12:12.896Z"
  },
  "updatedAt": {
    "$date": "2025-08-22T07:14:00.404Z"
  }
},
{
  "_id": {
    "$oid": "68a8184ce9320c1361e8af4e"
  },
  "id": 25,
  "name": "Jeruk Nipis",
  "qrCode": "KTD-JN-025",
  "owner": "Wati Susilowati",
  "fotoGambar": "https://picsum.photos/seed/jeruk-nipis/640/640",
  "memberId": "KOP-025",
  "contractNumber": "CTR-2023-08-025",
  "location": "Blok M, Zona 1",
  "plantType": "Buah",
  "status": "Pemupukan",
  "lastUpdate": "31/5/2025",
  "history": [
    {
      "id": 1,
      "type": "Pemupukan",
      "date": "31/5/2025",
      "description": "Pemupukan untuk jeruk nipis.",
      "hasImage": true,
      "imageUrl": null,
      "_id": {
        "$oid": "68a8184ce9320c1361e8af4f"
      }
    }
  ],
  "__v": 0,
  "createdAt": {
    "$date": "2025-08-22T07:12:12.896Z"
  },
  "updatedAt": {
    "$date": "2025-08-22T07:14:00.428Z"
  }
},
{
  "_id": {
    "$oid": "68a8184ce9320c1361e8af50"
  },
  "id": 26,
  "name": "Belimbing",
  "qrCode": "KTD-BL-026",
  "owner": "Yudi Setiawan",
  "fotoGambar": "https://picsum.photos/seed/belimbing/640/640",
  "memberId": "KOP-026",
  "contractNumber": "CTR-2023-08-026",
  "location": "Blok M, Zona 2",
  "plantType": "Buah",
  "status": "Tanam Bibit",
  "lastUpdate": "29/5/2025",
  "history": [
    {
      "id": 1,
      "type": "Tanam Bibit",
      "date": "29/5/2025",
      "description": "Penanaman bibit belimbing.",
      "hasImage": true,
      "imageUrl": null,
      "_id": {
        "$oid": "68a8184ce9320c1361e8af51"
      }
    }
  ],
  "__v": 0,
  "createdAt": {
    "$date": "2025-08-22T07:12:12.896Z"
  },
  "updatedAt": {
    "$date": "2025-08-22T07:14:00.451Z"
  }
},
{
  "_id": {
    "$oid": "68a8184ce9320c1361e8af52"
  },
  "id": 27,
  "name": "Jambu Air",
  "qrCode": "KTD-JA-027",
  "owner": "Sinta Dewi",
  "fotoGambar": "https://picsum.photos/seed/jambu-air/640/640",
  "memberId": "KOP-027",
  "contractNumber": "CTR-2023-08-027",
  "location": "Blok N, Zona 1",
  "plantType": "Buah",
  "status": "Persiapan Bibit",
  "lastUpdate": "27/5/2025",
  "history": [
    {
      "id": 1,
      "type": "Persiapan Bibit",
      "date": "27/5/2025",
      "description": "Bibit jambu air siap untuk penanaman.",
      "hasImage": true,
      "imageUrl": null,
      "_id": {
        "$oid": "68a8184ce9320c1361e8af53"
      }
    }
  ],
  "__v": 0,
  "createdAt": {
    "$date": "2025-08-22T07:12:12.896Z"
  },
  "updatedAt": {
    "$date": "2025-08-22T07:14:00.472Z"
  }
},
{
  "_id": {
    "$oid": "68a8184ce9320c1361e8af54"
  },
  "id": 28,
  "name": "Sawo",
  "qrCode": "KTD-SW-028",
  "owner": "Dani Pratama",
  "fotoGambar": "https://picsum.photos/seed/sawo/640/640",
  "memberId": "KOP-028",
  "contractNumber": "CTR-2023-08-028",
  "location": "Blok N, Zona 2",
  "plantType": "Buah",
  "status": "Kontrak Baru",
  "lastUpdate": "25/5/2025",
  "history": [
    {
      "id": 1,
      "type": "Kontrak Baru",
      "date": "25/5/2025",
      "description": "Kontrak penanaman sawo.",
      "hasImage": true,
      "imageUrl": null,
      "_id": {
        "$oid": "68a8184ce9320c1361e8af55"
      }
    }
  ],
  "__v": 0,
  "createdAt": {
    "$date": "2025-08-22T07:12:12.896Z"
  },
  "updatedAt": {
    "$date": "2025-08-22T07:14:00.493Z"
  }
},
{
  "_id": {
    "$oid": "68a8184ce9320c1361e8af56"
  },
  "id": 29,
  "name": "Nangka",
  "qrCode": "KTD-NK-029",
  "owner": "Lia Permata",
  "fotoGambar": "https://picsum.photos/seed/nangka/640/640",
  "memberId": "KOP-029",
  "contractNumber": "CTR-2023-08-029",
  "location": "Blok O, Zona 1",
  "plantType": "Buah",
  "status": "Pemupukan",
  "lastUpdate": "23/5/2025",
  "history": [
    {
      "id": 1,
      "type": "Pemupukan",
      "date": "23/5/2025",
      "description": "Pemupukan untuk tanaman nangka.",
      "hasImage": true,
      "imageUrl": null,
      "_id": {
        "$oid": "68a8184ce9320c1361e8af57"
      }
    }
  ],
  "__v": 0,
  "createdAt": {
    "$date": "2025-08-22T07:12:12.896Z"
  },
  "updatedAt": {
    "$date": "2025-08-22T07:14:00.516Z"
  }
},
{
  "_id": {
    "$oid": "68a8184ce9320c1361e8af58"
  },
  "id": 30,
  "name": "Sukun",
  "qrCode": "KTD-SK-030",
  "owner": "Andi Setiawan",
  "fotoGambar": "https://picsum.photos/seed/sukun/640/640",
  "memberId": "KOP-030",
  "contractNumber": "CTR-2023-08-030",
  "location": "Blok O, Zona 2",
  "plantType": "Buah",
  "status": "Tanam Bibit",
  "lastUpdate": "21/5/2025",
  "history": [
    {
      "id": 1,
      "type": "Tanam Bibit",
      "date": "21/5/2025",
      "description": "Penanaman bibit sukun.",
      "hasImage": true,
      "imageUrl": null,
      "_id": {
        "$oid": "68a8184ce9320c1361e8af59"
      }
    }
  ],
  "__v": 0,
  "createdAt": {
    "$date": "2025-08-22T07:12:12.897Z"
  },
  "updatedAt": {
    "$date": "2025-08-22T07:14:00.538Z"
  }
},
{
  "_id": {
    "$oid": "68a8184ce9320c1361e8af5a"
  },
  "id": 31,
  "name": "Petai",
  "qrCode": "KTD-PT-031",
  "owner": "Rini Astuti",
  "fotoGambar": "https://picsum.photos/seed/petai/640/640",
  "memberId": "KOP-031",
  "contractNumber": "CTR-2023-08-031",
  "location": "Blok P, Zona 1",
  "plantType": "Sayuran",
  "status": "Persiapan Bibit",
  "lastUpdate": "19/5/2025",
  "history": [
    {
      "id": 1,
      "type": "Persiapan Bibit",
      "date": "19/5/2025",
      "description": "Bibit petai siap untuk penanaman.",
      "hasImage": true,
      "imageUrl": null,
      "_id": {
        "$oid": "68a8184ce9320c1361e8af5b"
      }
    }
  ],
  "__v": 0,
  "createdAt": {
    "$date": "2025-08-22T07:12:12.897Z"
  },
  "updatedAt": {
    "$date": "2025-08-22T07:14:00.561Z"
  }
},
{
  "_id": {
    "$oid": "68a8184ce9320c1361e8af5c"
  },
  "id": 32,
  "name": "Melinjo",
  "qrCode": "KTD-ML-032",
  "owner": "Bayu Nugroho",
  "fotoGambar": "https://picsum.photos/seed/melinjo/640/640",
  "memberId": "KOP-032",
  "contractNumber": "CTR-2023-08-032",
  "location": "Blok P, Zona 2",
  "plantType": "Sayuran",
  "status": "Kontrak Baru",
  "lastUpdate": "17/5/2025",
  "history": [
    {
      "id": 1,
      "type": "Kontrak Baru",
      "date": "17/5/2025",
      "description": "Kontrak penanaman melinjo.",
      "hasImage": true,
      "imageUrl": null,
      "_id": {
        "$oid": "68a8184ce9320c1361e8af5d"
      }
    }
  ],
  "__v": 0,
  "createdAt": {
    "$date": "2025-08-22T07:12:12.897Z"
  },
  "updatedAt": {
    "$date": "2025-08-22T07:14:00.584Z"
  }
},
{
  "_id": {
    "$oid": "68a8184ce9320c1361e8af5e"
  },
  "id": 33,
  "name": "Bambu Betung",
  "qrCode": "KTD-BB-033",
  "owner": "Citra Sari",
  "fotoGambar": "https://picsum.photos/seed/bambu-betung/640/640",
  "memberId": "KOP-033",
  "contractNumber": "CTR-2023-08-033",
  "location": "Blok Q, Zona 1",
  "plantType": "Kayu",
  "status": "Pemupukan",
  "lastUpdate": "15/5/2025",
  "history": [
    {
      "id": 1,
      "type": "Pemupukan",
      "date": "15/5/2025",
      "description": "Pemupukan untuk bambu betung.",
      "hasImage": true,
      "imageUrl": null,
      "_id": {
        "$oid": "68a8184ce9320c1361e8af5f"
      }
    }
  ],
  "__v": 0,
  "createdAt": {
    "$date": "2025-08-22T07:12:12.897Z"
  },
  "updatedAt": {
    "$date": "2025-08-22T07:14:00.606Z"
  }
},
{
  "_id": {
    "$oid": "68a8184ce9320c1361e8af60"
  },
  "id": 34,
  "name": "Rotan",
  "qrCode": "KTD-RT-034",
  "owner": "Fajar Hidayat",
  "fotoGambar": "https://picsum.photos/seed/rotan/640/640",
  "memberId": "KOP-034",
  "contractNumber": "CTR-2023-08-034",
  "location": "Blok Q, Zona 2",
  "plantType": "Kayu",
  "status": "Tanam Bibit",
  "lastUpdate": "13/5/2025",
  "history": [
    {
      "id": 1,
      "type": "Tanam Bibit",
      "date": "13/5/2025",
      "description": "Penanaman bibit rotan.",
      "hasImage": true,
      "imageUrl": null,
      "_id": {
        "$oid": "68a8184ce9320c1361e8af61"
      }
    }
  ],
  "__v": 0,
  "createdAt": {
    "$date": "2025-08-22T07:12:12.897Z"
  },
  "updatedAt": {
    "$date": "2025-08-22T07:14:00.629Z"
  }
},
{
  "_id": {
    "$oid": "68a8184ce9320c1361e8af62"
  },
  "id": 35,
  "name": "Kayu Manis",
  "qrCode": "KTD-KM-035",
  "owner": "Gita Purnama",
  "fotoGambar": "https://picsum.photos/seed/kayu-manis/640/640",
  "memberId": "KOP-035",
  "contractNumber": "CTR-2023-08-035",
  "location": "Blok R, Zona 1",
  "plantType": "Rempah",
  "status": "Persiapan Bibit",
  "lastUpdate": "11/5/2025",
  "history": [
    {
      "id": 1,
      "type": "Persiapan Bibit",
      "date": "11/5/2025",
      "description": "Bibit kayu manis siap untuk penanaman.",
      "hasImage": true,
      "imageUrl": null,
      "_id": {
        "$oid": "68a8184ce9320c1361e8af63"
      }
    }
  ],
  "__v": 0,
  "createdAt": {
    "$date": "2025-08-22T07:12:12.897Z"
  },
  "updatedAt": {
    "$date": "2025-08-22T07:14:00.652Z"
  }
},
{
  "_id": {
    "$oid": "68a8184ce9320c1361e8af64"
  },
  "id": 36,
  "name": "Kapulaga",
  "qrCode": "KTD-KP-036",
  "owner": "Heru Santoso",
  "fotoGambar": "https://picsum.photos/seed/kapulaga/640/640",
  "memberId": "KOP-036",
  "contractNumber": "CTR-2023-08-036",
  "location": "Blok R, Zona 2",
  "plantType": "Rempah",
  "status": "Kontrak Baru",
  "lastUpdate": "9/5/2025",
  "history": [
    {
      "id": 1,
      "type": "Kontrak Baru",
      "date": "9/5/2025",
      "description": "Kontrak penanaman kapulaga.",
      "hasImage": true,
      "imageUrl": null,
      "_id": {
        "$oid": "68a8184ce9320c1361e8af65"
      }
    }
  ],
  "__v": 0,
  "createdAt": {
    "$date": "2025-08-22T07:12:12.897Z"
  },
  "updatedAt": {
    "$date": "2025-08-22T07:14:00.675Z"
  }
},
{
  "_id": {
    "$oid": "68a8184ce9320c1361e8af66"
  },
  "id": 37,
  "name": "Andaliman",
  "qrCode": "KTD-AD-037",
  "owner": "Ika Sari",
  "fotoGambar": "https://picsum.photos/seed/andaliman/640/640",
  "memberId": "KOP-037",
  "contractNumber": "CTR-2023-08-037",
  "location": "Blok S, Zona 1",
  "plantType": "Rempah",
  "status": "Pemupukan",
  "lastUpdate": "7/5/2025",
  "history": [
    {
      "id": 1,
      "type": "Pemupukan",
      "date": "7/5/2025",
      "description": "Pemupukan untuk andaliman.",
      "hasImage": true,
      "imageUrl": null,
      "_id": {
        "$oid": "68a8184ce9320c1361e8af67"
      }
    }
  ],
  "__v": 0,
  "createdAt": {
    "$date": "2025-08-22T07:12:12.897Z"
  },
  "updatedAt": {
    "$date": "2025-08-22T07:14:00.698Z"
  }
},
{
  "_id": {
    "$oid": "68a8184ce9320c1361e8af68"
  },
  "id": 38,
  "name": "Kemukus",
  "qrCode": "KTD-KS-038",
  "owner": "Jaka Pratama",
  "fotoGambar": "https://picsum.photos/seed/kemukus/640/640",
  "memberId": "KOP-038",
  "contractNumber": "CTR-2023-08-038",
  "location": "Blok S, Zona 2",
  "plantType": "Rempah",
  "status": "Tanam Bibit",
  "lastUpdate": "5/5/2025",
  "history": [
    {
      "id": 1,
      "type": "Tanam Bibit",
      "date": "5/5/2025",
      "description": "Penanaman bibit kemukus.",
      "hasImage": true,
      "imageUrl": null,
      "_id": {
        "$oid": "68a8184ce9320c1361e8af69"
      }
    }
  ],
  "__v": 0,
  "createdAt": {
    "$date": "2025-08-22T07:12:12.897Z"
  },
  "updatedAt": {
    "$date": "2025-08-22T07:14:00.720Z"
  }
},
{
  "_id": {
    "$oid": "68a8184ce9320c1361e8af6a"
  },
  "id": 39,
  "name": "Asam Jawa",
  "qrCode": "KTD-AJ-039",
  "owner": "Kiki Amelia",
  "fotoGambar": "https://picsum.photos/seed/asam-jawa/640/640",
  "memberId": "KOP-039",
  "contractNumber": "CTR-2023-08-039",
  "location": "Blok T, Zona 1",
  "plantType": "Buah",
  "status": "Persiapan Bibit",
  "lastUpdate": "3/5/2025",
  "history": [
    {
      "id": 1,
      "type": "Persiapan Bibit",
      "date": "3/5/2025",
      "description": "Bibit asam jawa siap untuk penanaman.",
      "hasImage": true,
      "imageUrl": null,
      "_id": {
        "$oid": "68a8184ce9320c1361e8af6b"
      }
    }
  ],
  "__v": 0,
  "createdAt": {
    "$date": "2025-08-22T07:12:12.897Z"
  },
  "updatedAt": {
    "$date": "2025-08-22T07:14:00.744Z"
  }
},
{
  "_id": {
    "$oid": "68a8184ce9320c1361e8af6c"
  },
  "id": 40,
  "name": "Kedondong",
  "qrCode": "KTD-KD-040",
  "owner": "Luki Hermawan",
  "fotoGambar": "https://picsum.photos/seed/kedondong/640/640",
  "memberId": "KOP-040",
  "contractNumber": "CTR-2023-08-040",
  "location": "Blok T, Zona 2",
  "plantType": "Buah",
  "status": "Kontrak Baru",
  "lastUpdate": "1/5/2025",
  "history": [
    {
      "id": 1,
      "type": "Kontrak Baru",
      "date": "1/5/2025",
      "description": "Kontrak penanaman kedondong.",
      "hasImage": true,
      "imageUrl": null,
      "_id": {
        "$oid": "68a8184ce9320c1361e8af6d"
      }
    }
  ],
  "__v": 0,
  "createdAt": {
    "$date": "2025-08-22T07:12:12.897Z"
  },
  "updatedAt": {
    "$date": "2025-08-22T07:14:00.766Z"
  }
},
{
  "_id": {
    "$oid": "68a8184ce9320c1361e8af6e"
  },
  "id": 41,
  "name": "Matoa",
  "qrCode": "KTD-MT-041",
  "owner": "Mira Sari",
  "fotoGambar": "https://picsum.photos/seed/matoa/640/640",
  "memberId": "KOP-041",
  "contractNumber": "CTR-2023-08-041",
  "location": "Blok U, Zona 1",
  "plantType": "Buah",
  "status": "Pemupukan",
  "lastUpdate": "29/4/2025",
  "history": [
    {
      "id": 1,
      "type": "Pemupukan",
      "date": "29/4/2025",
      "description": "Pemupukan untuk tanaman matoa.",
      "hasImage": true,
      "imageUrl": null,
      "_id": {
        "$oid": "68a8184ce9320c1361e8af6f"
      }
    }
  ],
  "__v": 0,
  "createdAt": {
    "$date": "2025-08-22T07:12:12.897Z"
  },
  "updatedAt": {
    "$date": "2025-08-22T07:14:00.791Z"
  }
},
{
  "_id": {
    "$oid": "68a8184ce9320c1361e8af70"
  },
  "id": 42,
  "name": "Duku",
  "qrCode": "KTD-DK-042",
  "owner": "Nanda Pratiwi",
  "fotoGambar": "https://picsum.photos/seed/duku/640/640",
  "memberId": "KOP-042",
  "contractNumber": "CTR-2023-08-042",
  "location": "Blok U, Zona 2",
  "plantType": "Buah",
  "status": "Tanam Bibit",
  "lastUpdate": "27/4/2025",
  "history": [
    {
      "id": 1,
      "type": "Tanam Bibit",
      "date": "27/4/2025",
      "description": "Penanaman bibit duku.",
      "hasImage": true,
      "imageUrl": null,
      "_id": {
        "$oid": "68a8184ce9320c1361e8af71"
      }
    }
  ],
  "__v": 0,
  "createdAt": {
    "$date": "2025-08-22T07:12:12.897Z"
  },
  "updatedAt": {
    "$date": "2025-08-22T07:14:00.813Z"
  }
},
{
  "_id": {
    "$oid": "68a8184ce9320c1361e8af72"
  },
  "id": 43,
  "name": "Langsat",
  "qrCode": "KTD-LS-043",
  "owner": "Oki Setiawan",
  "fotoGambar": "https://picsum.photos/seed/langsat/640/640",
  "memberId": "KOP-043",
  "contractNumber": "CTR-2023-08-043",
  "location": "Blok V, Zona 1",
  "plantType": "Buah",
  "status": "Persiapan Bibit",
  "lastUpdate": "25/4/2025",
  "history": [
    {
      "id": 1,
      "type": "Persiapan Bibit",
      "date": "25/4/2025",
      "description": "Bibit langsat siap untuk penanaman.",
      "hasImage": true,
      "imageUrl": null,
      "_id": {
        "$oid": "68a8184ce9320c1361e8af73"
      }
    }
  ],
  "__v": 0,
  "createdAt": {
    "$date": "2025-08-22T07:12:12.897Z"
  },
  "updatedAt": {
    "$date": "2025-08-22T07:14:00.836Z"
  }
},
{
  "_id": {
    "$oid": "68a8184ce9320c1361e8af74"
  },
  "id": 44,
  "name": "Rambai",
  "qrCode": "KTD-RB-044",
  "owner": "Putri Handayani",
  "fotoGambar": "https://picsum.photos/seed/rambai/640/640",
  "memberId": "KOP-044",
  "contractNumber": "CTR-2023-08-044",
  "location": "Blok V, Zona 2",
  "plantType": "Buah",
  "status": "Kontrak Baru",
  "lastUpdate": "23/4/2025",
  "history": [
    {
      "id": 1,
      "type": "Kontrak Baru",
      "date": "23/4/2025",
      "description": "Kontrak penanaman rambai.",
      "hasImage": true,
      "imageUrl": null,
      "_id": {
        "$oid": "68a8184ce9320c1361e8af75"
      }
    }
  ],
  "__v": 0,
  "createdAt": {
    "$date": "2025-08-22T07:12:12.897Z"
  },
  "updatedAt": {
    "$date": "2025-08-22T07:14:00.859Z"
  }
},
{
  "_id": {
    "$oid": "68a8184ce9320c1361e8af76"
  },
  "id": 45,
  "name": "Menteng",
  "qrCode": "KTD-MG-045",
  "owner": "Qori Maulana",
  "fotoGambar": "https://picsum.photos/seed/menteng/640/640",
  "memberId": "KOP-045",
  "contractNumber": "CTR-2023-08-045",
  "location": "Blok W, Zona 1",
  "plantType": "Buah",
  "status": "Pemupukan",
  "lastUpdate": "21/4/2025",
  "history": [
    {
      "id": 1,
      "type": "Pemupukan",
      "date": "21/4/2025",
      "description": "Pemupukan untuk tanaman menteng.",
      "hasImage": true,
      "imageUrl": null,
      "_id": {
        "$oid": "68a8184ce9320c1361e8af77"
      }
    }
  ],
  "__v": 0,
  "createdAt": {
    "$date": "2025-08-22T07:12:12.897Z"
  },
  "updatedAt": {
    "$date": "2025-08-22T07:14:00.882Z"
  }
},
{
  "_id": {
    "$oid": "68a8184ce9320c1361e8af78"
  },
  "id": 46,
  "name": "Bisbul",
  "qrCode": "KTD-BS-046",
  "owner": "Rina Wulandari",
  "fotoGambar": "https://picsum.photos/seed/bisbul/640/640",
  "memberId": "KOP-046",
  "contractNumber": "CTR-2023-08-046",
  "location": "Blok W, Zona 2",
  "plantType": "Buah",
  "status": "Tanam Bibit",
  "lastUpdate": "19/4/2025",
  "history": [
    {
      "id": 1,
      "type": "Tanam Bibit",
      "date": "19/4/2025",
      "description": "Penanaman bibit bisbul.",
      "hasImage": true,
      "imageUrl": null,
      "_id": {
        "$oid": "68a8184ce9320c1361e8af79"
      }
    }
  ],
  "__v": 0,
  "createdAt": {
    "$date": "2025-08-22T07:12:12.897Z"
  },
  "updatedAt": {
    "$date": "2025-08-22T07:14:00.906Z"
  }
},
{
  "_id": {
    "$oid": "68a8184ce9320c1361e8af7a"
  },
  "id": 47,
  "name": "Ceremai",
  "qrCode": "KTD-CR-047",
  "owner": "Sandi Kurniawan",
  "fotoGambar": "https://picsum.photos/seed/ceremai/640/640",
  "memberId": "KOP-047",
  "contractNumber": "CTR-2023-08-047",
  "location": "Blok X, Zona 1",
  "plantType": "Buah",
  "status": "Persiapan Bibit",
  "lastUpdate": "17/4/2025",
  "history": [
    {
      "id": 1,
      "type": "Persiapan Bibit",
      "date": "17/4/2025",
      "description": "Bibit ceremai siap untuk penanaman.",
      "hasImage": true,
      "imageUrl": null,
      "_id": {
        "$oid": "68a8184ce9320c1361e8af7b"
      }
    }
  ],
  "__v": 0,
  "createdAt": {
    "$date": "2025-08-22T07:12:12.897Z"
  },
  "updatedAt": {
    "$date": "2025-08-22T07:14:00.929Z"
  }
},
{
  "_id": {
    "$oid": "68a8184ce9320c1361e8af7c"
  },
  "id": 48,
  "name": "Kemang",
  "qrCode": "KTD-KG-048",
  "owner": "Tari Sari",
  "fotoGambar": "https://picsum.photos/seed/kemang/640/640",
  "memberId": "KOP-048",
  "contractNumber": "CTR-2023-08-048",
  "location": "Blok X, Zona 2",
  "plantType": "Buah",
  "status": "Kontrak Baru",
  "lastUpdate": "15/4/2025",
  "history": [
    {
      "id": 1,
      "type": "Kontrak Baru",
      "date": "15/4/2025",
      "description": "Kontrak penanaman kemang.",
      "hasImage": true,
      "imageUrl": null,
      "_id": {
        "$oid": "68a8184ce9320c1361e8af7d"
      }
    }
  ],
  "__v": 0,
  "createdAt": {
    "$date": "2025-08-22T07:12:12.898Z"
  },
  "updatedAt": {
    "$date": "2025-08-22T07:14:00.952Z"
  }
},
{
  "_id": {
    "$oid": "68a8184ce9320c1361e8af7e"
  },
  "id": 49,
  "name": "Gandaria",
  "qrCode": "KTD-GD-049",
  "owner": "Udin Setiawan",
  "fotoGambar": "https://picsum.photos/seed/gandaria/640/640",
  "memberId": "KOP-049",
  "contractNumber": "CTR-2023-08-049",
  "location": "Blok Y, Zona 1",
  "plantType": "Buah",
  "status": "Pemupukan",
  "lastUpdate": "13/4/2025",
  "history": [
    {
      "id": 1,
      "type": "Pemupukan",
      "date": "13/4/2025",
      "description": "Pemupukan untuk tanaman gandaria.",
      "hasImage": true,
      "imageUrl": null,
      "_id": {
        "$oid": "68a8184ce9320c1361e8af7f"
      }
    }
  ],
  "__v": 0,
  "createdAt": {
    "$date": "2025-08-22T07:12:12.898Z"
  },
  "updatedAt": {
    "$date": "2025-08-22T07:14:00.975Z"
  }
},
{
  "_id": {
    "$oid": "68a8184ce9320c1361e8af80"
  },
  "id": 50,
  "name": "Mundu",
  "qrCode": "KTD-MD-050",
  "owner": "Vina Marlina",
  "fotoGambar": "https://picsum.photos/seed/mundu/640/640",
  "memberId": "KOP-050",
  "contractNumber": "CTR-2023-08-050",
  "location": "Blok Y, Zona 2",
  "plantType": "Buah",
  "status": "Tanam Bibit",
  "lastUpdate": "11/4/2025",
  "history": [
    {
      "id": 1,
      "type": "Tanam Bibit",
      "date": "11/4/2025",
      "description": "Penanaman bibit mundu.",
      "hasImage": true,
      "imageUrl": null,
      "_id": {
        "$oid": "68a8184ce9320c1361e8af81"
      }
    }
  ],
  "__v": 0,
  "createdAt": {
    "$date": "2025-08-22T07:12:12.898Z"
  },
  "updatedAt": {
    "$date": "2025-08-22T07:14:00.998Z"
  }
},
{
  "_id": {
    "$oid": "68a8184ce9320c1361e8af82"
  },
  "id": 51,
  "name": "Durian Montong",
  "qrCode": "KTD-DM-051",
  "owner": "Sari Dewi",
  "fotoGambar": "https://picsum.photos/seed/durian-montong/640/640",
  "memberId": "KOP-051",
  "contractNumber": "CTR-2023-08-051",
  "location": "Blok A, Zona 1",
  "plantType": "Buah",
  "status": "Persiapan Bibit",
  "lastUpdate": "15/8/2025",
  "history": [
    {
      "id": 1,
      "type": "Persiapan Bibit",
      "date": "15/8/2025",
      "description": "Persiapan bibit durian montong tahap kedua.",
      "hasImage": true,
      "imageUrl": null,
      "_id": {
        "$oid": "68a8184ce9320c1361e8af83"
      }
    }
  ],
  "__v": 0,
  "createdAt": {
    "$date": "2025-08-22T07:12:12.898Z"
  },
  "updatedAt": {
    "$date": "2025-08-22T07:14:01.019Z"
  }
},
{
  "_id": {
    "$oid": "68a8184ce9320c1361e8af84"
  },
  "id": 52,
  "name": "Gaharu",
  "qrCode": "KTD-GH-052",
  "owner": "Andi Pratama",
  "fotoGambar": "https://picsum.photos/seed/gaharu/640/640",
  "memberId": "KOP-052",
  "contractNumber": "CTR-2023-08-052",
  "location": "Blok A, Zona 2",
  "plantType": "Kayu",
  "status": "Tanam Bibit",
  "lastUpdate": "18/8/2025",
  "history": [
    {
      "id": 1,
      "type": "Tanam Bibit",
      "date": "18/8/2025",
      "description": "Penanaman bibit gaharu di area baru.",
      "hasImage": true,
      "imageUrl": null,
      "_id": {
        "$oid": "68a8184ce9320c1361e8af85"
      }
    }
  ],
  "__v": 0,
  "createdAt": {
    "$date": "2025-08-22T07:12:12.898Z"
  },
  "updatedAt": {
    "$date": "2025-08-22T07:14:01.042Z"
  }
},
{
  "_id": {
    "$oid": "68a8184ce9320c1361e8af86"
  },
  "id": 53,
  "name": "Jengkol",
  "qrCode": "KTD-JK-053",
  "owner": "Rini Susanti",
  "fotoGambar": "https://picsum.photos/seed/jengkol/640/640",
  "memberId": "KOP-053",
  "contractNumber": "CTR-2023-08-053",
  "location": "Blok C, Zona 1",
  "plantType": "Buah",
  "status": "Pemupukan",
  "lastUpdate": "20/8/2025",
  "history": [
    {
      "id": 1,
      "type": "Pemupukan",
      "date": "20/8/2025",
      "description": "Pemupukan jengkol dengan pupuk organik.",
      "hasImage": true,
      "imageUrl": null,
      "_id": {
        "$oid": "68a8184ce9320c1361e8af87"
      }
    }
  ],
  "__v": 0,
  "createdAt": {
    "$date": "2025-08-22T07:12:12.898Z"
  },
  "updatedAt": {
    "$date": "2025-08-22T07:14:01.068Z"
  }
},
{
  "_id": {
    "$oid": "68a8184ce9320c1361e8af88"
  },
  "id": 54,
  "name": "Aren",
  "qrCode": "KTD-AR-054",
  "owner": "Budi Hartono",
  "fotoGambar": "https://picsum.photos/seed/aren/640/640",
  "memberId": "KOP-054",
  "contractNumber": "CTR-2023-08-054",
  "location": "Blok D, Zona 1",
  "plantType": "Industri",
  "status": "Penyiraman",
  "lastUpdate": "22/8/2025",
  "history": [
    {
      "id": 1,
      "type": "Penyiraman",
      "date": "22/8/2025",
      "description": "Penyiraman rutin tanaman aren.",
      "hasImage": true,
      "imageUrl": null,
      "_id": {
        "$oid": "68a8184ce9320c1361e8af89"
      }
    }
  ],
  "__v": 0,
  "createdAt": {
    "$date": "2025-08-22T07:12:12.898Z"
  },
  "updatedAt": {
    "$date": "2025-08-22T07:14:01.091Z"
  }
},
{
  "_id": {
    "$oid": "68a8184ce9320c1361e8af8a"
  },
  "id": 55,
  "name": "Alpukat",
  "qrCode": "KTD-AL-055",
  "owner": "Maya Sari",
  "fotoGambar": "https://picsum.photos/seed/alpukat/640/640",
  "memberId": "KOP-055",
  "contractNumber": "CTR-2023-08-055",
  "location": "Blok B, Zona 1",
  "plantType": "Buah",
  "status": "Pemangkasan",
  "lastUpdate": "25/8/2025",
  "history": [
    {
      "id": 1,
      "type": "Pemangkasan",
      "date": "25/8/2025",
      "description": "Pemangkasan cabang alpukat yang tidak produktif.",
      "hasImage": true,
      "imageUrl": null,
      "_id": {
        "$oid": "68a8184ce9320c1361e8af8b"
      }
    }
  ],
  "__v": 0,
  "createdAt": {
    "$date": "2025-08-22T07:12:12.898Z"
  },
  "updatedAt": {
    "$date": "2025-08-22T07:14:01.113Z"
  }
},
{
  "_id": {
    "$oid": "68a8184ce9320c1361e8af8c"
  },
  "id": 56,
  "name": "Jahe Merah",
  "qrCode": "KTD-JM-056",
  "owner": "Dedi Kurniawan",
  "fotoGambar": "https://picsum.photos/seed/jahe-merah/640/640",
  "memberId": "KOP-056",
  "contractNumber": "CTR-2023-08-056",
  "location": "Blok E, Zona 1",
  "plantType": "Rempah",
  "status": "Tanam Bibit",
  "lastUpdate": "28/8/2025",
  "history": [
    {
      "id": 1,
      "type": "Tanam Bibit",
      "date": "28/8/2025",
      "description": "Penanaman bibit jahe merah varietas unggul.",
      "hasImage": true,
      "imageUrl": null,
      "_id": {
        "$oid": "68a8184ce9320c1361e8af8d"
      }
    }
  ],
  "__v": 0,
  "createdAt": {
    "$date": "2025-08-22T07:12:12.898Z"
  },
  "updatedAt": {
    "$date": "2025-08-22T07:14:01.135Z"
  }
},
{
  "_id": {
    "$oid": "68a8184ce9320c1361e8af8e"
  },
  "id": 57,
  "name": "Jati",
  "qrCode": "KTD-JT-057",
  "owner": "Lina Marlina",
  "fotoGambar": "https://picsum.photos/seed/jati/640/640",
  "memberId": "KOP-057",
  "contractNumber": "CTR-2023-08-057",
  "location": "Blok F, Zona 1",
  "plantType": "Kayu",
  "status": "Persiapan Bibit",
  "lastUpdate": "30/8/2025",
  "history": [
    {
      "id": 1,
      "type": "Persiapan Bibit",
      "date": "30/8/2025",
      "description": "Persiapan bibit jati untuk penanaman.",
      "hasImage": true,
      "imageUrl": null,
      "_id": {
        "$oid": "68a8184ce9320c1361e8af8f"
      }
    }
  ],
  "__v": 0,
  "createdAt": {
    "$date": "2025-08-22T07:12:12.898Z"
  },
  "updatedAt": {
    "$date": "2025-08-22T07:14:01.157Z"
  }
},
{
  "_id": {
    "$oid": "68a8184ce9320c1361e8af90"
  },
  "id": 58,
  "name": "Kunyit",
  "qrCode": "KTD-KN-058",
  "owner": "Agus Salim",
  "fotoGambar": "https://picsum.photos/seed/kunyit/640/640",
  "memberId": "KOP-058",
  "contractNumber": "CTR-2023-08-058",
  "location": "Blok G, Zona 1",
  "plantType": "Rempah",
  "status": "Pemupukan",
  "lastUpdate": "2/9/2025",
  "history": [
    {
      "id": 1,
      "type": "Pemupukan",
      "date": "2/9/2025",
      "description": "Pemupukan kunyit dengan pupuk kandang.",
      "hasImage": true,
      "imageUrl": null,
      "_id": {
        "$oid": "68a8184ce9320c1361e8af91"
      }
    }
  ],
  "__v": 0,
  "createdAt": {
    "$date": "2025-08-22T07:12:12.898Z"
  },
  "updatedAt": {
    "$date": "2025-08-22T07:14:01.180Z"
  }
},
{
  "_id": {
    "$oid": "68a8184ce9320c1361e8af92"
  },
  "id": 59,
  "name": "Mangga",
  "qrCode": "KTD-MG-059",
  "owner": "Fitri Handayani",
  "fotoGambar": "https://picsum.photos/seed/mangga/640/640",
  "memberId": "KOP-059",
  "contractNumber": "CTR-2023-08-059",
  "location": "Blok H, Zona 1",
  "plantType": "Buah",
  "status": "Penyiraman",
  "lastUpdate": "5/9/2025",
  "history": [
    {
      "id": 1,
      "type": "Penyiraman",
      "date": "5/9/2025",
      "description": "Penyiraman mangga pada musim kemarau.",
      "hasImage": true,
      "imageUrl": null,
      "_id": {
        "$oid": "68a8184ce9320c1361e8af93"
      }
    }
  ],
  "__v": 0,
  "createdAt": {
    "$date": "2025-08-22T07:12:12.898Z"
  },
  "updatedAt": {
    "$date": "2025-08-22T07:14:01.202Z"
  }
},
{
  "_id": {
    "$oid": "68a8184ce9320c1361e8af94"
  },
  "id": 60,
  "name": "Lada",
  "qrCode": "KTD-LD-060",
  "owner": "Hendra Wijaya",
  "fotoGambar": "https://picsum.photos/seed/lada/640/640",
  "memberId": "KOP-060",
  "contractNumber": "CTR-2023-08-060",
  "location": "Blok I, Zona 1",
  "plantType": "Rempah",
  "status": "Pemangkasan",
  "lastUpdate": "8/9/2025",
  "history": [
    {
      "id": 1,
      "type": "Pemangkasan",
      "date": "8/9/2025",
      "description": "Pemangkasan tanaman lada untuk meningkatkan produktivitas.",
      "hasImage": true,
      "imageUrl": null,
      "_id": {
        "$oid": "68a8184ce9320c1361e8af95"
      }
    }
  ],
  "__v": 0,
  "createdAt": {
    "$date": "2025-08-22T07:12:12.898Z"
  },
  "updatedAt": {
    "$date": "2025-08-22T07:14:01.223Z"
  }
},
{
  "_id": {
    "$oid": "68a8184ce9320c1361e8af96"
  },
  "id": 61,
  "name": "Durian Montong",
  "qrCode": "KTD-DM-061",
  "owner": "Indra Gunawan",
  "fotoGambar": "https://picsum.photos/seed/durian-montong/640/640",
  "memberId": "KOP-061",
  "contractNumber": "CTR-2023-08-061",
  "location": "Blok A, Zona 1",
  "plantType": "Buah",
  "status": "Tanam Bibit",
  "lastUpdate": "10/9/2025",
  "history": [
    {
      "id": 1,
      "type": "Tanam Bibit",
      "date": "10/9/2025",
      "description": "Penanaman bibit durian montong generasi ketiga.",
      "hasImage": true,
      "imageUrl": null,
      "_id": {
        "$oid": "68a8184ce9320c1361e8af97"
      }
    }
  ],
  "__v": 0,
  "createdAt": {
    "$date": "2025-08-22T07:12:12.898Z"
  },
  "updatedAt": {
    "$date": "2025-08-22T07:14:01.247Z"
  }
},
{
  "_id": {
    "$oid": "68a8184ce9320c1361e8af98"
  },
  "id": 62,
  "name": "Gaharu",
  "qrCode": "KTD-GH-062",
  "owner": "Joko Susilo",
  "fotoGambar": "https://picsum.photos/seed/gaharu/640/640",
  "memberId": "KOP-062",
  "contractNumber": "CTR-2023-08-062",
  "location": "Blok A, Zona 2",
  "plantType": "Kayu",
  "status": "Persiapan Bibit",
  "lastUpdate": "12/9/2025",
  "history": [
    {
      "id": 1,
      "type": "Persiapan Bibit",
      "date": "12/9/2025",
      "description": "Persiapan bibit gaharu kualitas premium.",
      "hasImage": true,
      "imageUrl": null,
      "_id": {
        "$oid": "68a8184ce9320c1361e8af99"
      }
    }
  ],
  "__v": 0,
  "createdAt": {
    "$date": "2025-08-22T07:12:12.898Z"
  },
  "updatedAt": {
    "$date": "2025-08-22T07:14:01.270Z"
  }
},
{
  "_id": {
    "$oid": "68a8184ce9320c1361e8af9a"
  },
  "id": 63,
  "name": "Jengkol",
  "qrCode": "KTD-JK-063",
  "owner": "Kartini Sari",
  "fotoGambar": "https://picsum.photos/seed/jengkol/640/640",
  "memberId": "KOP-063",
  "contractNumber": "CTR-2023-08-063",
  "location": "Blok C, Zona 1",
  "plantType": "Buah",
  "status": "Pemupukan",
  "lastUpdate": "15/9/2025",
  "history": [
    {
      "id": 1,
      "type": "Pemupukan",
      "date": "15/9/2025",
      "description": "Pemupukan jengkol dengan NPK 16-16-16.",
      "hasImage": true,
      "imageUrl": null,
      "_id": {
        "$oid": "68a8184ce9320c1361e8af9b"
      }
    }
  ],
  "__v": 0,
  "createdAt": {
    "$date": "2025-08-22T07:12:12.898Z"
  },
  "updatedAt": {
    "$date": "2025-08-22T07:14:01.292Z"
  }
},
{
  "_id": {
    "$oid": "68a8184ce9320c1361e8af9c"
  },
  "id": 64,
  "name": "Aren",
  "qrCode": "KTD-AR-064",
  "owner": "Lukman Hakim",
  "fotoGambar": "https://picsum.photos/seed/aren/640/640",
  "memberId": "KOP-064",
  "contractNumber": "CTR-2023-08-064",
  "location": "Blok D, Zona 1",
  "plantType": "Industri",
  "status": "Penyiraman",
  "lastUpdate": "18/9/2025",
  "history": [
    {
      "id": 1,
      "type": "Penyiraman",
      "date": "18/9/2025",
      "description": "Penyiraman aren dengan sistem tetes.",
      "hasImage": true,
      "imageUrl": null,
      "_id": {
        "$oid": "68a8184ce9320c1361e8af9d"
      }
    }
  ],
  "__v": 0,
  "createdAt": {
    "$date": "2025-08-22T07:12:12.898Z"
  },
  "updatedAt": {
    "$date": "2025-08-22T07:14:01.316Z"
  }
},
{
  "_id": {
    "$oid": "68a8184ce9320c1361e8af9e"
  },
  "id": 65,
  "name": "Alpukat",
  "qrCode": "KTD-AL-065",
  "owner": "Mega Putri",
  "fotoGambar": "https://picsum.photos/seed/alpukat/640/640",
  "memberId": "KOP-065",
  "contractNumber": "CTR-2023-08-065",
  "location": "Blok B, Zona 1",
  "plantType": "Buah",
  "status": "Pemangkasan",
  "lastUpdate": "20/9/2025",
  "history": [
    {
      "id": 1,
      "type": "Pemangkasan",
      "date": "20/9/2025",
      "description": "Pemangkasan alpukat untuk pembentukan tajuk.",
      "hasImage": true,
      "imageUrl": null,
      "_id": {
        "$oid": "68a8184ce9320c1361e8af9f"
      }
    }
  ],
  "__v": 0,
  "createdAt": {
    "$date": "2025-08-22T07:12:12.898Z"
  },
  "updatedAt": {
    "$date": "2025-08-22T07:14:01.338Z"
  }
},
{
  "_id": {
    "$oid": "68a8184ce9320c1361e8afa0"
  },
  "id": 66,
  "name": "Jahe Merah",
  "qrCode": "KTD-JM-066",
  "owner": "Nana Suryani",
  "fotoGambar": "https://picsum.photos/seed/jahe-merah/640/640",
  "memberId": "KOP-066",
  "contractNumber": "CTR-2023-08-066",
  "location": "Blok E, Zona 1",
  "plantType": "Rempah",
  "status": "Tanam Bibit",
  "lastUpdate": "22/9/2025",
  "history": [
    {
      "id": 1,
      "type": "Tanam Bibit",
      "date": "22/9/2025",
      "description": "Penanaman jahe merah di lahan organik.",
      "hasImage": true,
      "imageUrl": null,
      "_id": {
        "$oid": "68a8184ce9320c1361e8afa1"
      }
    }
  ],
  "__v": 0,
  "createdAt": {
    "$date": "2025-08-22T07:12:12.898Z"
  },
  "updatedAt": {
    "$date": "2025-08-22T07:14:01.360Z"
  }
},
{
  "_id": {
    "$oid": "68a8184ce9320c1361e8afa2"
  },
  "id": 67,
  "name": "Jati",
  "qrCode": "KTD-JT-067",
  "owner": "Omar Bakri",
  "fotoGambar": "https://picsum.photos/seed/jati/640/640",
  "memberId": "KOP-067",
  "contractNumber": "CTR-2023-08-067",
  "location": "Blok F, Zona 1",
  "plantType": "Kayu",
  "status": "Persiapan Bibit",
  "lastUpdate": "25/9/2025",
  "history": [
    {
      "id": 1,
      "type": "Persiapan Bibit",
      "date": "25/9/2025",
      "description": "Persiapan bibit jati super untuk ekspor.",
      "hasImage": true,
      "imageUrl": null,
      "_id": {
        "$oid": "68a8184ce9320c1361e8afa3"
      }
    }
  ],
  "__v": 0,
  "createdAt": {
    "$date": "2025-08-22T07:12:12.898Z"
  },
  "updatedAt": {
    "$date": "2025-08-22T07:14:01.384Z"
  }
},
{
  "_id": {
    "$oid": "68a8184ce9320c1361e8afa4"
  },
  "id": 68,
  "name": "Kunyit",
  "qrCode": "KTD-KN-068",
  "owner": "Putri Maharani",
  "fotoGambar": "https://picsum.photos/seed/kunyit/640/640",
  "memberId": "KOP-068",
  "contractNumber": "CTR-2023-08-068",
  "location": "Blok G, Zona 1",
  "plantType": "Rempah",
  "status": "Pemupukan",
  "lastUpdate": "28/9/2025",
  "history": [
    {
      "id": 1,
      "type": "Pemupukan",
      "date": "28/9/2025",
      "description": "Pemupukan kunyit dengan kompos organik.",
      "hasImage": true,
      "imageUrl": null,
      "_id": {
        "$oid": "68a8184ce9320c1361e8afa5"
      }
    }
  ],
  "__v": 0,
  "createdAt": {
    "$date": "2025-08-22T07:12:12.898Z"
  },
  "updatedAt": {
    "$date": "2025-08-22T07:14:01.406Z"
  }
},
{
  "_id": {
    "$oid": "68a8184ce9320c1361e8afa6"
  },
  "id": 69,
  "name": "Mangga",
  "qrCode": "KTD-MG-069",
  "owner": "Qori Ananda",
  "fotoGambar": "https://picsum.photos/seed/mangga/640/640",
  "memberId": "KOP-069",
  "contractNumber": "CTR-2023-08-069",
  "location": "Blok H, Zona 1",
  "plantType": "Buah",
  "status": "Penyiraman",
  "lastUpdate": "30/9/2025",
  "history": [
    {
      "id": 1,
      "type": "Penyiraman",
      "date": "30/9/2025",
      "description": "Penyiraman mangga varietas harum manis.",
      "hasImage": true,
      "imageUrl": null,
      "_id": {
        "$oid": "68a8184ce9320c1361e8afa7"
      }
    }
  ],
  "__v": 0,
  "createdAt": {
    "$date": "2025-08-22T07:12:12.899Z"
  },
  "updatedAt": {
    "$date": "2025-08-22T07:14:01.429Z"
  }
},
{
  "_id": {
    "$oid": "68a8184ce9320c1361e8afa8"
  },
  "id": 70,
  "name": "Lada",
  "qrCode": "KTD-LD-070",
  "owner": "Rian Pratama",
  "fotoGambar": "https://picsum.photos/seed/lada/640/640",
  "memberId": "KOP-070",
  "contractNumber": "CTR-2023-08-070",
  "location": "Blok I, Zona 1",
  "plantType": "Rempah",
  "status": "Pemangkasan",
  "lastUpdate": "2/10/2025",
  "history": [
    {
      "id": 1,
      "type": "Pemangkasan",
      "date": "2/10/2025",
      "description": "Pemangkasan lada untuk merangsang pertumbuhan.",
      "hasImage": true,
      "imageUrl": null,
      "_id": {
        "$oid": "68a8184ce9320c1361e8afa9"
      }
    }
  ],
  "__v": 0,
  "createdAt": {
    "$date": "2025-08-22T07:12:12.899Z"
  },
  "updatedAt": {
    "$date": "2025-08-22T07:14:01.452Z"
  }
},
{
  "_id": {
    "$oid": "68a8184ce9320c1361e8afaa"
  },
  "id": 71,
  "name": "Mahoni",
  "qrCode": "KTD-MH-071",
  "owner": "Sinta Dewi",
  "fotoGambar": "https://picsum.photos/seed/mahoni/640/640",
  "memberId": "KOP-071",
  "contractNumber": "CTR-2023-08-071",
  "location": "Blok J, Zona 1",
  "plantType": "Kayu",
  "status": "Tanam Bibit",
  "lastUpdate": "5/10/2025",
  "history": [
    {
      "id": 1,
      "type": "Tanam Bibit",
      "date": "5/10/2025",
      "description": "Penanaman bibit mahoni untuk penghijauan.",
      "hasImage": true,
      "imageUrl": null,
      "_id": {
        "$oid": "68a8184ce9320c1361e8afab"
      }
    }
  ],
  "__v": 0,
  "createdAt": {
    "$date": "2025-08-22T07:12:12.899Z"
  },
  "updatedAt": {
    "$date": "2025-08-22T07:14:01.474Z"
  }
},
{
  "_id": {
    "$oid": "68a8184ce9320c1361e8afac"
  },
  "id": 72,
  "name": "Sengon",
  "qrCode": "KTD-SG-072",
  "owner": "Tono Sukirman",
  "fotoGambar": "https://picsum.photos/seed/sengon/640/640",
  "memberId": "KOP-072",
  "contractNumber": "CTR-2023-08-072",
  "location": "Blok K, Zona 1",
  "plantType": "Kayu",
  "status": "Persiapan Bibit",
  "lastUpdate": "8/10/2025",
  "history": [
    {
      "id": 1,
      "type": "Persiapan Bibit",
      "date": "8/10/2025",
      "description": "Persiapan bibit sengon untuk hutan tanaman.",
      "hasImage": true,
      "imageUrl": null,
      "_id": {
        "$oid": "68a8184ce9320c1361e8afad"
      }
    }
  ],
  "__v": 0,
  "createdAt": {
    "$date": "2025-08-22T07:12:12.899Z"
  },
  "updatedAt": {
    "$date": "2025-08-22T07:14:01.497Z"
  }
},
{
  "_id": {
    "$oid": "68a8184ce9320c1361e8afae"
  },
  "id": 73,
  "name": "Temulawak",
  "qrCode": "KTD-TL-073",
  "owner": "Umi Kalsum",
  "fotoGambar": "https://picsum.photos/seed/temulawak/640/640",
  "memberId": "KOP-073",
  "contractNumber": "CTR-2023-08-073",
  "location": "Blok L, Zona 1",
  "plantType": "Obat",
  "status": "Pemupukan",
  "lastUpdate": "10/10/2025",
  "history": [
    {
      "id": 1,
      "type": "Pemupukan",
      "date": "10/10/2025",
      "description": "Pemupukan temulawak dengan pupuk organik cair.",
      "hasImage": true,
      "imageUrl": null,
      "_id": {
        "$oid": "68a8184ce9320c1361e8afaf"
      }
    }
  ],
  "__v": 0,
  "createdAt": {
    "$date": "2025-08-22T07:12:12.899Z"
  },
  "updatedAt": {
    "$date": "2025-08-22T07:14:01.520Z"
  }
},
{
  "_id": {
    "$oid": "68a8184ce9320c1361e8afb0"
  },
  "id": 74,
  "name": "Kencur",
  "qrCode": "KTD-KC-074",
  "owner": "Vivi Andriani",
  "fotoGambar": "https://picsum.photos/seed/kencur/640/640",
  "memberId": "KOP-074",
  "contractNumber": "CTR-2023-08-074",
  "location": "Blok M, Zona 1",
  "plantType": "Obat",
  "status": "Penyiraman",
  "lastUpdate": "12/10/2025",
  "history": [
    {
      "id": 1,
      "type": "Penyiraman",
      "date": "12/10/2025",
      "description": "Penyiraman kencur dengan air sumur.",
      "hasImage": true,
      "imageUrl": null,
      "_id": {
        "$oid": "68a8184ce9320c1361e8afb1"
      }
    }
  ],
  "__v": 0,
  "createdAt": {
    "$date": "2025-08-22T07:12:12.899Z"
  },
  "updatedAt": {
    "$date": "2025-08-22T07:14:01.543Z"
  }
},
{
  "_id": {
    "$oid": "68a8184ce9320c1361e8afb2"
  },
  "id": 75,
  "name": "Lengkuas",
  "qrCode": "KTD-LK-075",
  "owner": "Wawan Setiawan",
  "fotoGambar": "https://picsum.photos/seed/lengkuas/640/640",
  "memberId": "KOP-075",
  "contractNumber": "CTR-2023-08-075",
  "location": "Blok N, Zona 1",
  "plantType": "Rempah",
  "status": "Pemangkasan",
  "lastUpdate": "15/10/2025",
  "history": [
    {
      "id": 1,
      "type": "Pemangkasan",
      "date": "15/10/2025",
      "description": "Pemangkasan lengkuas untuk panen rimpang.",
      "hasImage": true,
      "imageUrl": null,
      "_id": {
        "$oid": "68a8184ce9320c1361e8afb3"
      }
    }
  ],
  "__v": 0,
  "createdAt": {
    "$date": "2025-08-22T07:12:12.899Z"
  },
  "updatedAt": {
    "$date": "2025-08-22T07:14:01.565Z"
  }
},
{
  "_id": {
    "$oid": "68a8184ce9320c1361e8afb4"
  },
  "id": 76,
  "name": "Rambutan",
  "qrCode": "KTD-RB-076",
  "owner": "Xenia Putri",
  "fotoGambar": "https://picsum.photos/seed/rambutan/640/640",
  "memberId": "KOP-076",
  "contractNumber": "CTR-2023-08-076",
  "location": "Blok O, Zona 1",
  "plantType": "Buah",
  "status": "Tanam Bibit",
  "lastUpdate": "18/10/2025",
  "history": [
    {
      "id": 1,
      "type": "Tanam Bibit",
      "date": "18/10/2025",
      "description": "Penanaman bibit rambutan binjai.",
      "hasImage": true,
      "imageUrl": null,
      "_id": {
        "$oid": "68a8184ce9320c1361e8afb5"
      }
    }
  ],
  "__v": 0,
  "createdAt": {
    "$date": "2025-08-22T07:12:12.899Z"
  },
  "updatedAt": {
    "$date": "2025-08-22T07:14:01.588Z"
  }
},
{
  "_id": {
    "$oid": "68a8184ce9320c1361e8afb6"
  },
  "id": 77,
  "name": "Duku",
  "qrCode": "KTD-DK-077",
  "owner": "Yanto Wijaya",
  "fotoGambar": "https://picsum.photos/seed/duku/640/640",
  "memberId": "KOP-077",
  "contractNumber": "CTR-2023-08-077",
  "location": "Blok P, Zona 1",
  "plantType": "Buah",
  "status": "Persiapan Bibit",
  "lastUpdate": "20/10/2025",
  "history": [
    {
      "id": 1,
      "type": "Persiapan Bibit",
      "date": "20/10/2025",
      "description": "Persiapan bibit duku palembang.",
      "hasImage": true,
      "imageUrl": null,
      "_id": {
        "$oid": "68a8184ce9320c1361e8afb7"
      }
    }
  ],
  "__v": 0,
  "createdAt": {
    "$date": "2025-08-22T07:12:12.899Z"
  },
  "updatedAt": {
    "$date": "2025-08-22T07:14:01.611Z"
  }
},
{
  "_id": {
    "$oid": "68a8184ce9320c1361e8afb8"
  },
  "id": 78,
  "name": "Kelapa Sawit",
  "qrCode": "KTD-KS-078",
  "owner": "Zulkifli Ahmad",
  "fotoGambar": "https://picsum.photos/seed/kelapa-sawit/640/640",
  "memberId": "KOP-078",
  "contractNumber": "CTR-2023-08-078",
  "location": "Blok Q, Zona 1",
  "plantType": "Industri",
  "status": "Pemupukan",
  "lastUpdate": "22/10/2025",
  "history": [
    {
      "id": 1,
      "type": "Pemupukan",
      "date": "22/10/2025",
      "description": "Pemupukan kelapa sawit dengan pupuk majemuk.",
      "hasImage": true,
      "imageUrl": null,
      "_id": {
        "$oid": "68a8184ce9320c1361e8afb9"
      }
    }
  ],
  "__v": 0,
  "createdAt": {
    "$date": "2025-08-22T07:12:12.899Z"
  },
  "updatedAt": {
    "$date": "2025-08-22T07:14:01.633Z"
  }
},
{
  "_id": {
    "$oid": "68a8184ce9320c1361e8afba"
  },
  "id": 79,
  "name": "Karet",
  "qrCode": "KTD-KR-079",
  "owner": "Ani Suryani",
  "fotoGambar": "https://picsum.photos/seed/karet/640/640",
  "memberId": "KOP-079",
  "contractNumber": "CTR-2023-08-079",
  "location": "Blok R, Zona 1",
  "plantType": "Industri",
  "status": "Penyiraman",
  "lastUpdate": "25/10/2025",
  "history": [
    {
      "id": 1,
      "type": "Penyiraman",
      "date": "25/10/2025",
      "description": "Penyiraman karet pada musim kemarau.",
      "hasImage": true,
      "imageUrl": null,
      "_id": {
        "$oid": "68a8184ce9320c1361e8afbb"
      }
    }
  ],
  "__v": 0,
  "createdAt": {
    "$date": "2025-08-22T07:12:12.899Z"
  },
  "updatedAt": {
    "$date": "2025-08-22T07:14:01.656Z"
  }
},
{
  "_id": {
    "$oid": "68a8184ce9320c1361e8afbc"
  },
  "id": 80,
  "name": "Cengkeh",
  "qrCode": "KTD-CK-080",
  "owner": "Bambang Sutrisno",
  "fotoGambar": "https://picsum.photos/seed/cengkeh/640/640",
  "memberId": "KOP-080",
  "contractNumber": "CTR-2023-08-080",
  "location": "Blok S, Zona 1",
  "plantType": "Rempah",
  "status": "Pemangkasan",
  "lastUpdate": "28/10/2025",
  "history": [
    {
      "id": 1,
      "type": "Pemangkasan",
      "date": "28/10/2025",
      "description": "Pemangkasan cengkeh untuk meningkatkan produksi.",
      "hasImage": true,
      "imageUrl": null,
      "_id": {
        "$oid": "68a8184ce9320c1361e8afbd"
      }
    }
  ],
  "__v": 0,
  "createdAt": {
    "$date": "2025-08-22T07:12:12.899Z"
  },
  "updatedAt": {
    "$date": "2025-08-22T07:14:01.678Z"
  }
},
{
  "_id": {
    "$oid": "68a8184ce9320c1361e8afbe"
  },
  "id": 81,
  "name": "Pala",
  "qrCode": "KTD-PL-081",
  "owner": "Citra Dewi",
  "fotoGambar": "https://picsum.photos/seed/pala/640/640",
  "memberId": "KOP-081",
  "contractNumber": "CTR-2023-08-081",
  "location": "Blok T, Zona 1",
  "plantType": "Rempah",
  "status": "Tanam Bibit",
  "lastUpdate": "30/10/2025",
  "history": [
    {
      "id": 1,
      "type": "Tanam Bibit",
      "date": "30/10/2025",
      "description": "Penanaman bibit pala banda.",
      "hasImage": true,
      "imageUrl": null,
      "_id": {
        "$oid": "68a8184ce9320c1361e8afbf"
      }
    }
  ],
  "__v": 0,
  "createdAt": {
    "$date": "2025-08-22T07:12:12.899Z"
  },
  "updatedAt": {
    "$date": "2025-08-22T07:14:01.701Z"
  }
},
{
  "_id": {
    "$oid": "68a8184ce9320c1361e8afc0"
  },
  "id": 82,
  "name": "Kapulaga",
  "qrCode": "KTD-KP-082",
  "owner": "Dian Pratiwi",
  "fotoGambar": "https://picsum.photos/seed/kapulaga/640/640",
  "memberId": "KOP-082",
  "contractNumber": "CTR-2023-08-082",
  "location": "Blok U, Zona 1",
  "plantType": "Rempah",
  "status": "Persiapan Bibit",
  "lastUpdate": "2/11/2025",
  "history": [
    {
      "id": 1,
      "type": "Persiapan Bibit",
      "date": "2/11/2025",
      "description": "Persiapan bibit kapulaga lokal.",
      "hasImage": true,
      "imageUrl": null,
      "_id": {
        "$oid": "68a8184ce9320c1361e8afc1"
      }
    }
  ],
  "__v": 0,
  "createdAt": {
    "$date": "2025-08-22T07:12:12.899Z"
  },
  "updatedAt": {
    "$date": "2025-08-22T07:14:01.724Z"
  }
},
{
  "_id": {
    "$oid": "68a8184ce9320c1361e8afc2"
  },
  "id": 83,
  "name": "Vanili",
  "qrCode": "KTD-VN-083",
  "owner": "Eko Prasetyo",
  "fotoGambar": "https://picsum.photos/seed/vanili/640/640",
  "memberId": "KOP-083",
  "contractNumber": "CTR-2023-08-083",
  "location": "Blok V, Zona 1",
  "plantType": "Rempah",
  "status": "Pemupukan",
  "lastUpdate": "5/11/2025",
  "history": [
    {
      "id": 1,
      "type": "Pemupukan",
      "date": "5/11/2025",
      "description": "Pemupukan vanili dengan pupuk organik.",
      "hasImage": true,
      "imageUrl": null,
      "_id": {
        "$oid": "68a8184ce9320c1361e8afc3"
      }
    }
  ],
  "__v": 0,
  "createdAt": {
    "$date": "2025-08-22T07:12:12.899Z"
  },
  "updatedAt": {
    "$date": "2025-08-22T07:14:01.746Z"
  }
},
{
  "_id": {
    "$oid": "68a8184ce9320c1361e8afc4"
  },
  "id": 84,
  "name": "Kemiri",
  "qrCode": "KTD-KM-084",
  "owner": "Fajar Nugroho",
  "fotoGambar": "https://picsum.photos/seed/kemiri/640/640",
  "memberId": "KOP-084",
  "contractNumber": "CTR-2023-08-084",
  "location": "Blok W, Zona 1",
  "plantType": "Industri",
  "status": "Penyiraman",
  "lastUpdate": "8/11/2025",
  "history": [
    {
      "id": 1,
      "type": "Penyiraman",
      "date": "8/11/2025",
      "description": "Penyiraman kemiri dengan sistem sprinkler.",
      "hasImage": true,
      "imageUrl": null,
      "_id": {
        "$oid": "68a8184ce9320c1361e8afc5"
      }
    }
  ],
  "__v": 0,
  "createdAt": {
    "$date": "2025-08-22T07:12:12.899Z"
  },
  "updatedAt": {
    "$date": "2025-08-22T07:14:01.769Z"
  }
},
{
  "_id": {
    "$oid": "68a8184ce9320c1361e8afc6"
  },
  "id": 85,
  "name": "Jambu Mete",
  "qrCode": "KTD-JMT-085",
  "owner": "Gita Sari",
  "fotoGambar": "https://picsum.photos/seed/jambu-mete/640/640",
  "memberId": "KOP-085",
  "contractNumber": "CTR-2023-08-085",
  "location": "Blok X, Zona 1",
  "plantType": "Buah",
  "status": "Pemangkasan",
  "lastUpdate": "10/11/2025",
  "history": [
    {
      "id": 1,
      "type": "Pemangkasan",
      "date": "10/11/2025",
      "description": "Pemangkasan jambu mete untuk pembentukan kanopi.",
      "hasImage": true,
      "imageUrl": null,
      "_id": {
        "$oid": "68a8184ce9320c1361e8afc7"
      }
    }
  ],
  "__v": 0,
  "createdAt": {
    "$date": "2025-08-22T07:12:12.899Z"
  },
  "updatedAt": {
    "$date": "2025-08-22T07:14:01.791Z"
  }
},
{
  "_id": {
    "$oid": "68a8184ce9320c1361e8afc8"
  },
  "id": 86,
  "name": "Gandaria",
  "qrCode": "KTD-GD-086",
  "owner": "Hadi Susanto",
  "fotoGambar": "https://picsum.photos/seed/gandaria/640/640",
  "memberId": "KOP-086",
  "contractNumber": "CTR-2023-08-086",
  "location": "Blok Y, Zona 1",
  "plantType": "Buah",
  "status": "Tanam Bibit",
  "lastUpdate": "12/11/2025",
  "history": [
    {
      "id": 1,
      "type": "Tanam Bibit",
      "date": "12/11/2025",
      "description": "Penanaman bibit gandaria lokal.",
      "hasImage": true,
      "imageUrl": null,
      "_id": {
        "$oid": "68a8184ce9320c1361e8afc9"
      }
    }
  ],
  "__v": 0,
  "createdAt": {
    "$date": "2025-08-22T07:12:12.899Z"
  },
  "updatedAt": {
    "$date": "2025-08-22T07:14:01.812Z"
  }
},
{
  "_id": {
    "$oid": "68a8184ce9320c1361e8afca"
  },
  "id": 87,
  "name": "Mundu",
  "qrCode": "KTD-MD-087",
  "owner": "Ika Rahayu",
  "fotoGambar": "https://picsum.photos/seed/mundu/640/640",
  "memberId": "KOP-087",
  "contractNumber": "CTR-2023-08-087",
  "location": "Blok Y, Zona 2",
  "plantType": "Buah",
  "status": "Persiapan Bibit",
  "lastUpdate": "15/11/2025",
  "history": [
    {
      "id": 1,
      "type": "Persiapan Bibit",
      "date": "15/11/2025",
      "description": "Persiapan bibit mundu untuk ekspansi.",
      "hasImage": true,
      "imageUrl": null,
      "_id": {
        "$oid": "68a8184ce9320c1361e8afcb"
      }
    }
  ],
  "__v": 0,
  "createdAt": {
    "$date": "2025-08-22T07:12:12.899Z"
  },
  "updatedAt": {
    "$date": "2025-08-22T07:14:01.835Z"
  }
},
{
  "_id": {
    "$oid": "68a8184ce9320c1361e8afcc"
  },
  "id": 88,
  "name": "Durian Montong",
  "qrCode": "KTD-DM-088",
  "owner": "Jaka Sembiring",
  "fotoGambar": "https://picsum.photos/seed/durian-montong/640/640",
  "memberId": "KOP-088",
  "contractNumber": "CTR-2023-08-088",
  "location": "Blok A, Zona 1",
  "plantType": "Buah",
  "status": "Pemupukan",
  "lastUpdate": "18/11/2025",
  "history": [
    {
      "id": 1,
      "type": "Pemupukan",
      "date": "18/11/2025",
      "description": "Pemupukan durian montong dengan pupuk slow release.",
      "hasImage": true,
      "imageUrl": null,
      "_id": {
        "$oid": "68a8184ce9320c1361e8afcd"
      }
    }
  ],
  "__v": 0,
  "createdAt": {
    "$date": "2025-08-22T07:12:12.899Z"
  },
  "updatedAt": {
    "$date": "2025-08-22T07:14:01.858Z"
  }
},
{
  "_id": {
    "$oid": "68a8184ce9320c1361e8afce"
  },
  "id": 89,
  "name": "Gaharu",
  "qrCode": "KTD-GH-089",
  "owner": "Kiki Amelia",
  "fotoGambar": "https://picsum.photos/seed/gaharu/640/640",
  "memberId": "KOP-089",
  "contractNumber": "CTR-2023-08-089",
  "location": "Blok A, Zona 2",
  "plantType": "Kayu",
  "status": "Penyiraman",
  "lastUpdate": "20/11/2025",
  "history": [
    {
      "id": 1,
      "type": "Penyiraman",
      "date": "20/11/2025",
      "description": "Penyiraman gaharu dengan air hujan.",
      "hasImage": true,
      "imageUrl": null,
      "_id": {
        "$oid": "68a8184ce9320c1361e8afcf"
      }
    }
  ],
  "__v": 0,
  "createdAt": {
    "$date": "2025-08-22T07:12:12.900Z"
  },
  "updatedAt": {
    "$date": "2025-08-22T07:14:01.881Z"
  }
},
{
  "_id": {
    "$oid": "68a8184ce9320c1361e8afd0"
  },
  "id": 90,
  "name": "Jengkol",
  "qrCode": "KTD-JK-090",
  "owner": "Lilis Suryani",
  "fotoGambar": "https://picsum.photos/seed/jengkol/640/640",
  "memberId": "KOP-090",
  "contractNumber": "CTR-2023-08-090",
  "location": "Blok C, Zona 1",
  "plantType": "Buah",
  "status": "Pemangkasan",
  "lastUpdate": "22/11/2025",
  "history": [
    {
      "id": 1,
      "type": "Pemangkasan",
      "date": "22/11/2025",
      "description": "Pemangkasan jengkol untuk meningkatkan ventilasi.",
      "hasImage": true,
      "imageUrl": null,
      "_id": {
        "$oid": "68a8184ce9320c1361e8afd1"
      }
    }
  ],
  "__v": 0,
  "createdAt": {
    "$date": "2025-08-22T07:12:12.900Z"
  },
  "updatedAt": {
    "$date": "2025-08-22T07:14:01.903Z"
  }
},
{
  "_id": {
    "$oid": "68a8184ce9320c1361e8afd2"
  },
  "id": 91,
  "name": "Aren",
  "qrCode": "KTD-AR-091",
  "owner": "Maman Suryaman",
  "fotoGambar": "https://picsum.photos/seed/aren/640/640",
  "memberId": "KOP-091",
  "contractNumber": "CTR-2023-08-091",
  "location": "Blok D, Zona 1",
  "plantType": "Industri",
  "status": "Tanam Bibit",
  "lastUpdate": "25/11/2025",
  "history": [
    {
      "id": 1,
      "type": "Tanam Bibit",
      "date": "25/11/2025",
      "description": "Penanaman bibit aren untuk produksi gula.",
      "hasImage": true,
      "imageUrl": null,
      "_id": {
        "$oid": "68a8184ce9320c1361e8afd3"
      }
    }
  ],
  "__v": 0,
  "createdAt": {
    "$date": "2025-08-22T07:12:12.900Z"
  },
  "updatedAt": {
    "$date": "2025-08-22T07:14:01.926Z"
  }
},
{
  "_id": {
    "$oid": "68a8184ce9320c1361e8afd4"
  },
  "id": 92,
  "name": "Alpukat",
  "qrCode": "KTD-AL-092",
  "owner": "Nina Kartika",
  "fotoGambar": "https://picsum.photos/seed/alpukat/640/640",
  "memberId": "KOP-092",
  "contractNumber": "CTR-2023-08-092",
  "location": "Blok B, Zona 1",
  "plantType": "Buah",
  "status": "Persiapan Bibit",
  "lastUpdate": "28/11/2025",
  "history": [
    {
      "id": 1,
      "type": "Persiapan Bibit",
      "date": "28/11/2025",
      "description": "Persiapan bibit alpukat mentega.",
      "hasImage": true,
      "imageUrl": null,
      "_id": {
        "$oid": "68a8184ce9320c1361e8afd5"
      }
    }
  ],
  "__v": 0,
  "createdAt": {
    "$date": "2025-08-22T07:12:12.900Z"
  },
  "updatedAt": {
    "$date": "2025-08-22T07:14:01.949Z"
  }
},
{
  "_id": {
    "$oid": "68a8184ce9320c1361e8afd6"
  },
  "id": 93,
  "name": "Jahe Merah",
  "qrCode": "KTD-JM-093",
  "owner": "Oki Setiawan",
  "fotoGambar": "https://picsum.photos/seed/jahe-merah/640/640",
  "memberId": "KOP-093",
  "contractNumber": "CTR-2023-08-093",
  "location": "Blok E, Zona 1",
  "plantType": "Rempah",
  "status": "Pemupukan",
  "lastUpdate": "30/11/2025",
  "history": [
    {
      "id": 1,
      "type": "Pemupukan",
      "date": "30/11/2025",
      "description": "Pemupukan jahe merah dengan pupuk hayati.",
      "hasImage": true,
      "imageUrl": null,
      "_id": {
        "$oid": "68a8184ce9320c1361e8afd7"
      }
    }
  ],
  "__v": 0,
  "createdAt": {
    "$date": "2025-08-22T07:12:12.900Z"
  },
  "updatedAt": {
    "$date": "2025-08-22T07:14:01.972Z"
  }
},
{
  "_id": {
    "$oid": "68a8184ce9320c1361e8afd8"
  },
  "id": 94,
  "name": "Jati",
  "qrCode": "KTD-JT-094",
  "owner": "Pandu Winata",
  "fotoGambar": "https://picsum.photos/seed/jati/640/640",
  "memberId": "KOP-094",
  "contractNumber": "CTR-2023-08-094",
  "location": "Blok F, Zona 1",
  "plantType": "Kayu",
  "status": "Penyiraman",
  "lastUpdate": "2/12/2025",
  "history": [
    {
      "id": 1,
      "type": "Penyiraman",
      "date": "2/12/2025",
      "description": "Penyiraman jati dengan sistem irigasi tetes.",
      "hasImage": true,
      "imageUrl": null,
      "_id": {
        "$oid": "68a8184ce9320c1361e8afd9"
      }
    }
  ],
  "__v": 0,
  "createdAt": {
    "$date": "2025-08-22T07:12:12.900Z"
  },
  "updatedAt": {
    "$date": "2025-08-22T07:14:01.996Z"
  }
},
{
  "_id": {
    "$oid": "68a8184ce9320c1361e8afda"
  },
  "id": 95,
  "name": "Kunyit",
  "qrCode": "KTD-KN-095",
  "owner": "Qonita Sari",
  "fotoGambar": "https://picsum.photos/seed/kunyit/640/640",
  "memberId": "KOP-095",
  "contractNumber": "CTR-2023-08-095",
  "location": "Blok G, Zona 1",
  "plantType": "Rempah",
  "status": "Pemangkasan",
  "lastUpdate": "5/12/2025",
  "history": [
    {
      "id": 1,
      "type": "Pemangkasan",
      "date": "5/12/2025",
      "description": "Pemangkasan kunyit untuk panen rimpang.",
      "hasImage": true,
      "imageUrl": null,
      "_id": {
        "$oid": "68a8184ce9320c1361e8afdb"
      }
    }
  ],
  "__v": 0,
  "createdAt": {
    "$date": "2025-08-22T07:12:12.900Z"
  },
  "updatedAt": {
    "$date": "2025-08-22T07:14:02.019Z"
  }
},
{
  "_id": {
    "$oid": "68a8184ce9320c1361e8afdc"
  },
  "id": 96,
  "name": "Mangga",
  "qrCode": "KTD-MG-096",
  "owner": "Rian Hidayat",
  "fotoGambar": "https://picsum.photos/seed/mangga/640/640",
  "memberId": "KOP-096",
  "contractNumber": "CTR-2023-08-096",
  "location": "Blok H, Zona 1",
  "plantType": "Buah",
  "status": "Tanam Bibit",
  "lastUpdate": "8/12/2025",
  "history": [
    {
      "id": 1,
      "type": "Tanam Bibit",
      "date": "8/12/2025",
      "description": "Penanaman bibit mangga gedong gincu.",
      "hasImage": true,
      "imageUrl": null,
      "_id": {
        "$oid": "68a8184ce9320c1361e8afdd"
      }
    }
  ],
  "__v": 0,
  "createdAt": {
    "$date": "2025-08-22T07:12:12.900Z"
  },
  "updatedAt": {
    "$date": "2025-08-22T07:14:02.043Z"
  }
},
{
  "_id": {
    "$oid": "68a8184ce9320c1361e8afde"
  },
  "id": 97,
  "name": "Lada",
  "qrCode": "KTD-LD-097",
  "owner": "Sari Indah",
  "fotoGambar": "https://picsum.photos/seed/lada/640/640",
  "memberId": "KOP-097",
  "contractNumber": "CTR-2023-08-097",
  "location": "Blok I, Zona 1",
  "plantType": "Rempah",
  "status": "Persiapan Bibit",
  "lastUpdate": "10/12/2025",
  "history": [
    {
      "id": 1,
      "type": "Persiapan Bibit",
      "date": "10/12/2025",
      "description": "Persiapan bibit lada putih premium.",
      "hasImage": true,
      "imageUrl": null,
      "_id": {
        "$oid": "68a8184ce9320c1361e8afdf"
      }
    }
  ],
  "__v": 0,
  "createdAt": {
    "$date": "2025-08-22T07:12:12.900Z"
  },
  "updatedAt": {
    "$date": "2025-08-22T07:14:02.066Z"
  }
},
{
  "_id": {
    "$oid": "68a8184ce9320c1361e8afe0"
  },
  "id": 98,
  "name": "Mahoni",
  "qrCode": "KTD-MH-098",
  "owner": "Taufik Rahman",
  "fotoGambar": "https://picsum.photos/seed/mahoni/640/640",
  "memberId": "KOP-098",
  "contractNumber": "CTR-2023-08-098",
  "location": "Blok J, Zona 1",
  "plantType": "Kayu",
  "status": "Pemupukan",
  "lastUpdate": "12/12/2025",
  "history": [
    {
      "id": 1,
      "type": "Pemupukan",
      "date": "12/12/2025",
      "description": "Pemupukan mahoni dengan pupuk NPK.",
      "hasImage": true,
      "imageUrl": null,
      "_id": {
        "$oid": "68a8184ce9320c1361e8afe1"
      }
    }
  ],
  "__v": 0,
  "createdAt": {
    "$date": "2025-08-22T07:12:12.900Z"
  },
  "updatedAt": {
    "$date": "2025-08-22T07:14:02.089Z"
  }
},
{
  "_id": {
    "$oid": "68a8184ce9320c1361e8afe2"
  },
  "id": 99,
  "name": "Sengon",
  "qrCode": "KTD-SG-099",
  "owner": "Umi Salamah",
  "fotoGambar": "https://picsum.photos/seed/sengon/640/640",
  "memberId": "KOP-099",
  "contractNumber": "CTR-2023-08-099",
  "location": "Blok K, Zona 1",
  "plantType": "Kayu",
  "status": "Penyiraman",
  "lastUpdate": "15/12/2025",
  "history": [
    {
      "id": 1,
      "type": "Penyiraman",
      "date": "15/12/2025",
      "description": "Penyiraman sengon pada musim kemarau.",
      "hasImage": true,
      "imageUrl": null,
      "_id": {
        "$oid": "68a8184ce9320c1361e8afe3"
      }
    }
  ],
  "__v": 0,
  "createdAt": {
    "$date": "2025-08-22T07:12:12.900Z"
  },
  "updatedAt": {
    "$date": "2025-08-22T07:14:02.112Z"
  }
},
{
  "_id": {
    "$oid": "68a8184ce9320c1361e8afe4"
  },
  "id": 100,
  "name": "Temulawak",
  "qrCode": "KTD-TL-100",
  "owner": "Vicky Pratama",
  "fotoGambar": "https://picsum.photos/seed/temulawak/640/640",
  "memberId": "KOP-100",
  "contractNumber": "CTR-2023-08-100",
  "location": "Blok L, Zona 1",
  "plantType": "Obat",
  "status": "Pemangkasan",
  "lastUpdate": "18/12/2025",
  "history": [
    {
      "id": 1,
      "type": "Pemangkasan",
      "date": "18/12/2025",
      "description": "Pemangkasan temulawak untuk meningkatkan kualitas rimpang.",
      "hasImage": true,
      "imageUrl": null,
      "_id": {
        "$oid": "68a8184ce9320c1361e8afe5"
      }
    }
  ],
  "__v": 0,
  "createdAt": {
    "$date": "2025-08-22T07:12:12.900Z"
  },
  "updatedAt": {
    "$date": "2025-08-22T07:14:02.136Z"
  }
},
{
  "_id": {
    "$oid": "68a8189be9320c1361e8afe7"
  },
  "id": 101,
  "name": "Gaharu",
  "qrCode": "KTD-GH-101",
  "owner": "Sari Dewi",
  "fotoGambar": "https://picsum.photos/seed/gaharu/640/640",
  "memberId": "KOP-101",
  "contractNumber": "CTR-2023-08-101",
  "location": "Blok B, Zona 1",
  "plantType": "Kayu",
  "status": "Tanam Bibit",
  "lastUpdate": "22/12/2025",
  "history": [
    {
      "id": 1,
      "type": "Tanam Bibit",
      "date": "22/12/2025",
      "description": "Penanaman bibit gaharu super unggul di lokasi baru.",
      "hasImage": true,
      "imageUrl": null,
      "_id": {
        "$oid": "68a8189be9320c1361e8afe8"
      }
    }
  ],
  "__v": 0,
  "createdAt": {
    "$date": "2025-08-22T07:13:31.689Z"
  },
  "updatedAt": {
    "$date": "2025-08-22T07:14:02.161Z"
  }
},
{
  "_id": {
    "$oid": "68a8189be9320c1361e8afe9"
  },
  "id": 102,
  "name": "Gaharu",
  "qrCode": "KTD-GH-102",
  "owner": "Bambang Wijaya",
  "fotoGambar": "https://picsum.photos/seed/gaharu/640/640",
  "memberId": "KOP-102",
  "contractNumber": "CTR-2023-08-102",
  "location": "Blok C, Zona 3",
  "plantType": "Kayu",
  "status": "Persiapan Bibit",
  "lastUpdate": "21/12/2025",
  "history": [
    {
      "id": 1,
      "type": "Persiapan Bibit",
      "date": "21/12/2025",
      "description": "Persiapan bibit gaharu varietas lokal unggulan.",
      "hasImage": true,
      "imageUrl": null,
      "_id": {
        "$oid": "68a8189be9320c1361e8afea"
      }
    }
  ],
  "__v": 0,
  "createdAt": {
    "$date": "2025-08-22T07:13:31.690Z"
  },
  "updatedAt": {
    "$date": "2025-08-22T07:14:02.184Z"
  }
},
{
  "_id": {
    "$oid": "68a8189be9320c1361e8afeb"
  },
  "id": 103,
  "name": "Gaharu",
  "qrCode": "KTD-GH-103",
  "owner": "Indira Sari",
  "fotoGambar": "https://picsum.photos/seed/gaharu/640/640",
  "memberId": "KOP-103",
  "contractNumber": "CTR-2023-08-103",
  "location": "Blok D, Zona 2",
  "plantType": "Kayu",
  "status": "Pemupukan",
  "lastUpdate": "20/12/2025",
  "history": [
    {
      "id": 1,
      "type": "Pemupukan",
      "date": "20/12/2025",
      "description": "Pemberian pupuk organik untuk pertumbuhan optimal gaharu.",
      "hasImage": true,
      "imageUrl": null,
      "_id": {
        "$oid": "68a8189be9320c1361e8afec"
      }
    }
  ],
  "__v": 0,
  "createdAt": {
    "$date": "2025-08-22T07:13:31.690Z"
  },
  "updatedAt": {
    "$date": "2025-08-22T07:14:02.207Z"
  }
},
{
  "_id": {
    "$oid": "68a8189be9320c1361e8afed"
  },
  "id": 104,
  "name": "Gaharu",
  "qrCode": "KTD-GH-104",
  "owner": "Rudi Hartono",
  "fotoGambar": "https://picsum.photos/seed/gaharu/640/640",
  "memberId": "KOP-104",
  "contractNumber": "CTR-2023-08-104",
  "location": "Blok E, Zona 1",
  "plantType": "Kayu",
  "status": "Penyiraman",
  "lastUpdate": "19/12/2025",
  "history": [
    {
      "id": 1,
      "type": "Penyiraman",
      "date": "19/12/2025",
      "description": "Penyiraman rutin gaharu dengan sistem tetes.",
      "hasImage": true,
      "imageUrl": null,
      "_id": {
        "$oid": "68a8189be9320c1361e8afee"
      }
    }
  ],
  "__v": 0,
  "createdAt": {
    "$date": "2025-08-22T07:13:31.690Z"
  },
  "updatedAt": {
    "$date": "2025-08-22T07:14:02.230Z"
  }
},
{
  "_id": {
    "$oid": "68a8189be9320c1361e8afef"
  },
  "id": 105,
  "name": "Gaharu",
  "qrCode": "KTD-GH-105",
  "owner": "Maya Kusuma",
  "fotoGambar": "https://picsum.photos/seed/gaharu/640/640",
  "memberId": "KOP-105",
  "contractNumber": "CTR-2023-08-105",
  "location": "Blok F, Zona 4",
  "plantType": "Kayu",
  "status": "Kontrak Baru",
  "lastUpdate": "18/12/2025",
  "history": [
    {
      "id": 1,
      "type": "Kontrak Baru",
      "date": "18/12/2025",
      "description": "Kontrak penanaman gaharu baru dengan target 5 tahun.",
      "hasImage": true,
      "imageUrl": null,
      "_id": {
        "$oid": "68a8189be9320c1361e8aff0"
      }
    }
  ],
  "__v": 0,
  "createdAt": {
    "$date": "2025-08-22T07:13:31.690Z"
  },
  "updatedAt": {
    "$date": "2025-08-22T07:14:02.253Z"
  }
},
{
  "_id": {
    "$oid": "68a82db0f38ea46805cf2fd2"
  },
  "id": 106,
  "name": "test ben",
  "qrCode": "PL-1755852208521",
  "owner": "ben",
  "fotoGambar": null,
  "memberId": "68a7e13d5c3defd0077476be",
  "contractNumber": "CTR-2025-1755852208521",
  "location": "test",
  "plantType": "Pohon",
  "status": "Tanam Bibit",
  "lastUpdate": "2025-08-29",
  "history": [
    {
      "id": 1,
      "type": "Tanam Bibit",
      "date": "2025-08-29",
      "description": "Penanaman test ben di lokasi test.",
      "hasImage": false,
      "imageUrl": null,
      "_id": {
        "$oid": "68a82db0f38ea46805cf2fd3"
      }
    }
  ],
  "createdAt": {
    "$date": "2025-08-22T08:43:28.811Z"
  },
  "updatedAt": {
    "$date": "2025-08-22T08:43:28.811Z"
  },
  "__v": 0
}]